{
  "batch": "0057",
  "range": "atcoder:1781-1810 (ABC369C-ABC373D, 30 problems)",
  "kind": "O",
  "assignments": [
    { "pid": "atcoder:1781", "chapterId": "cpp-6-10-2", "title": "ABC369C Count Arithmetic Subarrays",      "reason": "线性DP基础与状态设计：维护当前连续等差段长度，累加每个位置作为右端点的贡献" },
    { "pid": "atcoder:1782", "chapterId": "cpp-6-10-2", "title": "ABC369D Bonus EXP",                        "reason": "线性DP基础与状态设计：dp[i][parity] 表示打到第i个怪物且已击败数量奇偶性时的最大经验值" },
    { "pid": "atcoder:1783", "chapterId": "cpp-9-4-2",  "title": "ABC369E Sightseeing Tour",                 "reason": "状压DP经典（TSP/最小覆盖）：先做全源最短路，再对必经桥两端点做状态压缩转移" },
    { "pid": "atcoder:1784", "chapterId": "cpp-6-10-3", "title": "ABC369F Gather Coins",                     "reason": "LIS模型：把硬币按坐标排序后转成二维最长不下降链，并回溯构造具体路径" },
    { "pid": "atcoder:1785", "chapterId": "cpp-7-10-1", "title": "ABC369G As far as possible",               "reason": "树形DP基础框架：根据被选顶点集合在树上的覆盖深度分析最坏情况下的往返长度" },
    { "pid": "atcoder:1786", "chapterId": "cpp-1-4-5",  "title": "ABC370A Raise Both Hands",                 "reason": "if-else if 多分支：根据L和R的组合输出Yes、No或Invalid" },
    { "pid": "atcoder:1787", "chapterId": "cpp-4-2-1",  "title": "ABC370B Binary Alchemy",                   "reason": "矩阵的定义与遍历：按给定下三角表模拟元素依次合成的过程" },
    { "pid": "atcoder:1788", "chapterId": "cpp-5-8-3",  "title": "ABC370C Word Ladder",                      "reason": "贪心经典例题：每次优先修改最靠前且能让当前字符串字典序更小的位置，构造最优序列" },
    { "pid": "atcoder:1789", "chapterId": "cpp-5-2-3",  "title": "ABC370D Cross Explosion",                  "reason": "set/map：每行每列维护尚未摧毁的墙位置，支持查找上下左右最近墙并删除" },
    { "pid": "atcoder:1790", "chapterId": "cpp-6-10-2", "title": "ABC370E Avoid K Partition",                "reason": "线性DP基础与状态设计：前缀和+哈希维护所有合法分割数，排除和为K的最后一段" },
    { "pid": "atcoder:1791", "chapterId": "cpp-5-6-2",  "title": "ABC370F Cake Division",                    "reason": "二分答案：二分最小分块质量，检查环形蛋糕是否能切成至少K段并统计未切线数" },
    { "pid": "atcoder:1792", "chapterId": "cpp-7-3-2",  "title": "ABC370G Divisible by 3",                   "reason": "矩阵快速幂：按素因子状态转移计数好整数序列，快速处理超大M" },
    { "pid": "atcoder:1793", "chapterId": "cpp-1-4-1",  "title": "ABC371A Jiro",                             "reason": "if/else 单分支与双分支：根据三组大小关系判断年龄居中的兄弟是谁" },
    { "pid": "atcoder:1794", "chapterId": "cpp-5-2-3",  "title": "ABC371B Taro",                             "reason": "set/map：记录每个家族是否已经出现过男性婴儿，按序输出是否命名为太郎" },
    { "pid": "atcoder:1795", "chapterId": "cpp-3-5-2",  "title": "ABC371C Make Isomorphic",                  "reason": "二进制枚举：小N下枚举顶点置换，计算把图H改成与G同构所需的最小总代价" },
    { "pid": "atcoder:1796", "chapterId": "cpp-5-6-1",  "title": "ABC371D 1D Country",                       "reason": "二分查找：对有序村庄坐标做前缀人口和，二分区间端点回答总人口查询" },
    { "pid": "atcoder:1797", "chapterId": "cpp-5-5-1",  "title": "ABC371E I Hate Sigma Problems",            "reason": "前缀和基础：用每个值上次出现位置统计其对所有子数组不同元素数的贡献" },
    { "pid": "atcoder:1798", "chapterId": "cpp-8-11-1", "title": "ABC371F Takahashi in Narrow Road",         "reason": "线段树基础：维护人员相对顺序与位移代价，处理指定人到达目标位置的最小总移动次数" },
    { "pid": "atcoder:1799", "chapterId": "cpp-6-9-1",  "title": "ABC371G Lexicographically Smallest Permutation", "reason": "DFS基本框架：置换分解成若干循环，在循环内枚举旋转找到字典序最小结果" },
    { "pid": "atcoder:1800", "chapterId": "cpp-3-2-5",  "title": "ABC372A delete .",                         "reason": "字符串查找与替换：删除字符串中的所有点字符并输出剩余部分" },
    { "pid": "atcoder:1801", "chapterId": "cpp-3-3-1",  "title": "ABC372B 3^A",                              "reason": "二进制与十进制转换：把M分解为若干个3的幂次和，等价于三进制展开" },
    { "pid": "atcoder:1802", "chapterId": "cpp-3-2-5",  "title": "ABC372C Count ABC Again",                  "reason": "字符串查找与替换：每次修改只需重查位置附近长度3的子串，维护ABC出现次数" },
    { "pid": "atcoder:1803", "chapterId": "cpp-7-8-1",  "title": "ABC372D Buildings",                        "reason": "单调栈贪心：从右往左维护可见建筑的单调结构，统计每栋楼能看到的数量" },
    { "pid": "atcoder:1804", "chapterId": "cpp-8-2-1",  "title": "ABC372E K-th Largest Connected Components", "reason": "并查集基础：合并连通块时只保留每个块最大的若干顶点编号，回答第k大查询" },
    { "pid": "atcoder:1805", "chapterId": "cpp-7-3-2",  "title": "ABC372F Teleporting Takahashi 2",          "reason": "矩阵快速幂：把一步转移建成线性递推，计算恰好K步的路径方案数" },
    { "pid": "atcoder:1806", "chapterId": "cpp-9-10-3", "title": "ABC372G Ax + By < C",                      "reason": "计算几何点积叉积与凸包：把线性不等式组视为半平面约束，统计正整数解点数" },
    { "pid": "atcoder:1807", "chapterId": "cpp-1-5-1",  "title": "ABC373A September",                        "reason": "for循环基础：遍历12个字符串，统计长度恰好等于序号的个数" },
    { "pid": "atcoder:1808", "chapterId": "cpp-3-6-1",  "title": "ABC373B 1D Keyboard",                      "reason": "数组模拟栈/队列：记录每个字母在排列中的位置，按A到Z累加相邻移动距离" },
    { "pid": "atcoder:1809", "chapterId": "cpp-1-4-2",  "title": "ABC373C Max Ai+Bj",                        "reason": "最值和排序：分别求出A和B中的最大值，相加即为答案" },
    { "pid": "atcoder:1810", "chapterId": "cpp-6-9-1",  "title": "ABC373D Hidden Weights",                   "reason": "DFS基本框架：在图上沿边传播顶点权值差，求出一组满足约束的解" }
  ]
}