{
  "count": 26,
  "items": [
    {
      "_id": "69c5e387d215db96b04308a6",
      "questionUid": "downloads-1109-q3",
      "adminNote": "",
      "detail": "",
      "issueType": "wrong_answer",
      "levelTag": "gesp1",
      "paperQuestionNo": 3,
      "reportedAt": "2026-03-27T01:55:19.795Z",
      "reporterName": "kunkka",
      "source": "downloads",
      "sourceDocId": 1109,
      "sourceTitle": "1109 - 2024 BCSP-X 涓嬪崐骞存椿鍔ㄥ熀纭€鐭ヨ瘑娴嬭瘎锛堝皬瀛︿綆骞寸骇缁勶級",
      "status": "pending",
      "tags": [
        "downloads-import",
        "objective",
        "csp",
        "bcsp",
        "鏁板鍩虹",
        "椤哄簭缁撴瀯"
      ],
      "type": "single",
      "question": {
        "_id": "69c0b260d215db96b0110b35",
        "questionUid": "downloads-1109-q3",
        "answer": "B",
        "enabled": true,
        "explanation": "杩欓亾棰樿€冩煡鐨勬槸瀵?C++ 绠楁湳杩愮畻绗︼紙鏁撮櫎 `/` 鍜屽彇妯?`%`锛夌殑鐞嗚В浠ュ強閫昏緫寤烘ā鑳藉姏銆俓n\n1. **閫昏緫鍒嗘瀽**锛歕n   - 娲诲姩瑙勫垯鏄€滀拱 3 鐡堕€?1 鐡垛€濄€傝繖鎰忓懗鐫€姣忚姳 3 鍏冮挶锛屼綘瀹為檯涓婂彲浠ュ緱鍒?4 鐡舵按锛堜拱鐨?3 鐡?+ 閫佺殑 1 鐡讹級銆俓n   - 鍋囪浣犳湁 $x$ 鍏冮挶锛屾瘡鐡舵按 1 鍏冦€俓n   - 浣犲彲浠ュ厛璁＄畻鍑?$x$ 鍏冮挶閲屽寘鍚灏戜釜鈥? 鍏冣€濓細鏁伴噺涓?`x / 3`锛圕++ 涓殑鏁撮櫎锛夈€俓n   - 姣忎竴涓€? 鍏冣€濊兘璁╀綘鑾峰緱 4 鐡舵按锛屾墍浠ヨ繖閮ㄥ垎鎬绘暟鏄?`(x / 3) * 4`銆俓n   - 鍓╀笅鐨勯挶涓嶈冻 3 鍏冿紝鏃犳硶鍙傚姞淇冮攢锛屽彧鑳芥寜鍘熶环璐拱锛氭暟閲忎负 `x % 3`銆俓n   - 鎬荤摱鏁?= `(x / 3) * 4 + x % 3`銆俓n\n2. **琛ㄨ揪寮忕畝鍖栦笌楠岃瘉**锛歕n   - 鎴戜滑鏉ラ獙璇侀€夐」 B锛歚4 * x / 3`銆俓n   - 鍦?C++ 涓紝`4 * x / 3` 绛変环浜庢暟瀛︿笂鐨?$\\lfloor \\frac{4x}{3} \\rfloor$銆俓n   - 璁╂垜浠唬鍏ュ叿浣撴暟鍊兼祴璇曪細\n     - 鑻?$x = 3$锛歕n       - 閫昏緫璁＄畻锛氫拱 3 閫?1锛屽叡 4 鐡躲€俓n       - 閫夐」 B锛歚4 * 3 / 3 = 4`銆傛纭€俓n     - 鑻?$x = 4$锛歕n       - 閫昏緫璁＄畻锛氳姳 3 鍏冨緱 4 鐡讹紝鍓?1 鍏冧拱 1 鐡讹紝鍏?5 鐡躲€俓n       - 閫夐」 B锛歚4 * 4 / 3 = 16 / 3 = 5`銆傛纭€俓n     - 鑻?$x = 5$锛歕n       - 閫昏緫璁＄畻锛氳姳 3 鍏冨緱 4 鐡讹紝鍓?2 鍏冧拱 2 鐡讹紝鍏?6 鐡躲€俓n       - 閫夐」 B锛歚4 * 5 / 3 = 20 / 3 = 6`銆傛纭€俓n   - 浜嬪疄涓婏紝鏁板涓?$x + \\lfloor \\frac{x}{3} \\rfloor$锛堝師鏈夌殑閽变拱鐨勭摱鏁?+ 璧犻€佺殑鐡舵暟锛変笌 $\\lfloor \\frac{4x}{3} \\rfloor$ 鍦ㄦ暣鏁拌繍绠椾笅鏄瓑浠风殑銆俓n\n3. **鍏朵粬閫夐」鍒嗘瀽**锛歕n   - A 閫夐」 `3 * x + 1`锛氭樉鐒堕敊璇紝閽辫秺澶氱摱鏁板憟 3 鍊嶅闀匡紝涓嶇鍚堥€昏緫銆俓n   - C 閫夐」 `4 * x / 3 + x % 3`锛氬湪 $x=4$ 鏃讹紝缁撴灉涓?`5 + 1 = 6`锛岃€屽疄闄呭彧鑳藉緱 5 鐡讹紝澶氱畻浜嗕綑鏁般€俓n   - D 閫夐」 `4 * x % 3 + x / 3`锛氶€昏緫瀹屽叏閿欒銆俓n\n鍥犳锛屾纭瓟妗堟槸 B銆?,
        "explanationText": "杩欓亾棰樿€冩煡鐨勬槸瀵?C++ 绠楁湳杩愮畻绗︼紙鏁撮櫎 / 鍜屽彇妯?%锛夌殑鐞嗚В浠ュ強閫昏緫寤烘ā鑳藉姏銆?1. 閫昏緫鍒嗘瀽锛?- 娲诲姩瑙勫垯鏄€滀拱 3 鐡堕€?1 鐡垛€濄€傝繖鎰忓懗鐫€姣忚姳 3 鍏冮挶锛屼綘瀹為檯涓婂彲浠ュ緱鍒?4 鐡舵按锛堜拱鐨?3 鐡?+ 閫佺殑 1 鐡讹級銆?- 鍋囪浣犳湁 $x$ 鍏冮挶锛屾瘡鐡舵按 1 鍏冦€?- 浣犲彲浠ュ厛璁＄畻鍑?$x$ 鍏冮挶閲屽寘鍚灏戜釜鈥? 鍏冣€濓細鏁伴噺涓?x / 3锛圕++ 涓殑鏁撮櫎锛夈€?- 姣忎竴涓€? 鍏冣€濊兘璁╀綘鑾峰緱 4 鐡舵按锛屾墍浠ヨ繖閮ㄥ垎鎬绘暟鏄?(x / 3) * 4銆?- 鍓╀笅鐨勯挶涓嶈冻 3 鍏冿紝鏃犳硶鍙傚姞淇冮攢锛屽彧鑳芥寜鍘熶环璐拱锛氭暟閲忎负 x % 3銆?- 鎬荤摱鏁?= (x / 3) * 4 + x % 3銆?2. 琛ㄨ揪寮忕畝鍖栦笌楠岃瘉锛?- 鎴戜滑鏉ラ獙璇侀€夐」 B锛? * x / 3銆?- 鍦?C++ 涓紝4 * x / 3 绛変环浜庢暟瀛︿笂鐨?$\\lfloor \\frac{4x}{3} \\rfloor$銆?- 璁╂垜浠唬鍏ュ叿浣撴暟鍊兼祴璇曪細 - 鑻?$x = 3$锛?- 閫昏緫璁＄畻锛氫拱 3 閫?1锛屽叡 4 鐡躲€?- 閫夐」 B锛? * 3 / 3 = 4銆傛纭€?- 鑻?$x = 4$锛?- 閫昏緫璁＄畻锛氳姳 3 鍏冨緱 4 鐡讹紝鍓?1 鍏冧拱 1 鐡讹紝鍏?5 鐡躲€?- 閫夐」 B锛? * 4 / 3 = 16 / 3 = 5銆傛纭€?- 鑻?$x = 5$锛?- 閫昏緫璁＄畻锛氳姳 3 鍏冨緱 4 鐡讹紝鍓?2 鍏冧拱 2 鐡讹紝鍏?6 鐡躲€?- 閫夐」 B锛? * 5 / 3 = 20 / 3 = 6銆傛纭€?- 浜嬪疄涓婏紝鏁板涓?$x + \\lfloor \\frac{x}{3} \\rfloor$锛堝師鏈夌殑閽变拱鐨勭摱鏁?+ 璧犻€佺殑鐡舵暟锛変笌 $\\lfloor \\frac{4x}{3} \\rfloor$ 鍦ㄦ暣鏁拌繍绠椾笅鏄瓑浠风殑銆?3. 鍏朵粬閫夐」鍒嗘瀽锛?- A 閫夐」 3 * x + 1锛氭樉鐒堕敊璇紝閽辫秺澶氱摱鏁板憟 3 鍊嶅闀匡紝涓嶇鍚堥€昏緫銆?- C 閫夐」 4 * x / 3 + x % 3锛氬湪 $x=4$ 鏃讹紝缁撴灉涓?5 + 1 = 6锛岃€屽疄闄呭彧鑳藉緱 5 鐡讹紝澶氱畻浜嗕綑鏁般€?- D 閫夐」 4 * x % 3 + x / 3锛氶€昏緫瀹屽叏閿欒銆?鍥犳锛屾纭瓟妗堟槸 B銆?,
        "levelTag": "gesp1",
        "options": [
          {
            "key": "A",
            "text": "3 * x + 1",
            "textPlain": "3 * x + 1",
            "images": []
          },
          {
            "key": "B",
            "text": "4 * x / 3",
            "textPlain": "4 * x / 3",
            "images": []
          },
          {
            "key": "C",
            "text": "4 * x / 3 + x % 3",
            "textPlain": "4 * x / 3 + x % 3",
            "images": []
          },
          {
            "key": "D",
            "text": "4 * x % 3 + x / 3",
            "textPlain": "4 * x % 3 + x / 3",
            "images": []
          }
        ],
        "reviewStatus": "pending",
        "stem": "浣犲幓瓒呭競涔扮熆娉夋按锛屽彂鐜拌秴甯傚湪杩涜淇冮攢娲诲姩锛氫拱 3 鐡堕€?1 鐡讹紝鍋囪涓€鐡剁熆娉夋按 1 鍏冿紝浣犳墜閲屾湁 x 鍏冿紙x 鏄鏁存暟锛夛紝浠ヤ笅鍝釜 C++ 鐨勮〃杈惧紡鑳藉璁＄畻鍑烘渶澶氬彲浠ヨ喘涔板灏戠摱鐭挎硥姘达細锛?锛?,
        "stemText": "浣犲幓瓒呭競涔扮熆娉夋按锛屽彂鐜拌秴甯傚湪杩涜淇冮攢娲诲姩锛氫拱 3 鐡堕€?1 鐡讹紝鍋囪涓€鐡剁熆娉夋按 1 鍏冿紝浣犳墜閲屾湁 x 鍏冿紙x 鏄鏁存暟锛夛紝浠ヤ笅鍝釜 C++ 鐨勮〃杈惧紡鑳藉璁＄畻鍑烘渶澶氬彲浠ヨ喘涔板灏戠摱鐭挎硥姘达細锛?锛?,
        "tags": [
          "downloads-import",
          "objective",
          "csp",
          "bcsp",
          "鏁板鍩虹",
          "椤哄簭缁撴瀯"
        ],
        "type": "single",
        "updatedAt": "2026-03-26T13:03:17.244Z"
      }
    },
    {
      "_id": "69c53b9ad215db96b03cff37",
      "questionUid": "gesp-2024-09-cpp-1-q4",
      "adminNote": "",
      "detail": "",
      "issueType": "other",
      "levelTag": "gesp1",
      "paperQuestionNo": 4,
      "reportedAt": "2026-03-26T13:58:50.979Z",
      "reporterName": "瀛欏槈褰?,
      "source": "gesp",
      "sourceDocId": 271,
      "sourceTitle": "GESP-C++-2024骞?鏈堜竴绾х湡棰樺嵎GESP-C++-2024骞?鏈堜竴绾х湡棰樺嵎",
      "status": "pending",
      "tags": [
        "鏁板鍩虹"
      ],
      "type": "single",
      "question": {
        "_id": "69beb5e2d215db96b0fd0329",
        "questionUid": "gesp-2024-09-cpp-1-q4",
        "answer": "",
        "enabled": true,
        "explanation": "",
        "explanationText": "",
        "levelTag": "gesp1",
        "options": [
          {
            "key": "A",
            "text": "14",
            "textPlain": "14",
            "images": []
          },
          {
            "key": "B",
            "text": "4",
            "textPlain": "4",
            "images": []
          },
          {
            "key": "C",
            "text": "1",
            "textPlain": "1",
            "images": []
          },
          {
            "key": "D",
            "text": "0",
            "textPlain": "0",
            "images": []
          }
        ],
        "reviewStatus": "pending",
        "stem": "C++琛ㄨ揪寮?`10 - 3 * 2` 鐨勫€兼槸( )銆?,
        "stemText": "C++琛ㄨ揪寮?10 - 3 * 2 鐨勫€兼槸( )銆?,
        "tags": [
          "鏁板鍩虹"
        ],
        "type": "single",
        "updatedAt": "2026-03-26T13:58:28.993Z"
      }
    },
    {
      "_id": "69c5367ed215db96b03cbf54",
      "questionUid": "gesp-2024-09-cpp-3-q20",
      "adminNote": "",
      "detail": "鏃犻€夐」",
      "issueType": "other",
      "levelTag": "gesp3",
      "paperQuestionNo": 20,
      "reportedAt": "2026-03-26T13:37:02.493Z",
      "reporterName": "鏉庨噾閾?,
      "source": "gesp",
      "sourceDocId": 273,
      "sourceTitle": "GESP-C++-2024骞?鏈堜笁绾х湡棰樺嵎GESP-C++-2024骞?鏈堜笁绾х湡棰樺嵎",
      "status": "pending",
      "tags": [
        "椤哄簭缁撴瀯"
      ],
      "type": "judge",
      "question": {
        "_id": "69beb5e2d215db96b0fd036a",
        "questionUid": "gesp-2024-09-cpp-3-q20",
        "answer": "false",
        "enabled": true,
        "explanation": "璁╂垜浠€愯鍒嗘瀽杩欐 C++ 浠ｇ爜锛歕n\n1.  `char x = 65;`\n    *   杩欒浠ｇ爜澹版槑浜嗕竴涓瓧绗﹀瀷鍙橀噺 `x`锛屽苟灏嗗叾鍒濆鍖栦负鏁存暟鍊?`65`銆俓n    *   鍦?ASCII 缂栫爜涓紝鏁存暟 `65` 瀵瑰簲鐨勫瓧绗︽槸 'A'銆傛墍浠ワ紝姝ゆ椂 `x` 鐨勫€间负 'A'銆俓n\n2.  `x++;`\n    *   杩欒浠ｇ爜瀵瑰彉閲?`x` 鎵ц浜嗗悗缃嚜澧炴搷浣溿€俓n    *   `x` 鐨勫€间粠 'A' (ASCII 65) 澧炲姞 1锛屽彉涓?'B' (ASCII 66)銆俓n    *   姝ゆ椂锛宍x` 鐨勫€间负 'B'銆俓n\n3.  `cout << x++ << endl;`\n    *   杩欒浠ｇ爜灏?`x` 鐨勫€艰緭鍑哄埌鎺у埗鍙帮紝鐒跺悗鎹㈣銆俓n    *   杩欓噷鐨?`x++` 涔熸槸涓€涓悗缃嚜澧炴搷浣滅銆傚畠鐨勮涓烘槸锛歕n        *   棣栧厛锛屼娇鐢?`x` 鐨勫綋鍓嶅€艰繘琛岃緭鍑恒€俓n        *   鐒跺悗锛屽湪杈撳嚭瀹屾垚鍚庯紝`x` 鐨勫€煎啀鑷 1銆俓n    *   鍦ㄦ墽琛屽埌杩欒鏃讹紝`x` 鐨勫綋鍓嶅€兼槸 'B' (ASCII 66)銆俓n    *   鎵€浠ワ紝`cout` 浼氳緭鍑哄瓧绗?'B'銆俓n    *   杈撳嚭瀹屾垚鍚庯紝`x` 鐨勫€间細浠?'B' (ASCII 66) 鑷鍒?'C' (ASCII 67)銆備絾杩欎釜 'C' 涓嶄細鍦ㄨ繖琛屼唬鐮佷腑琚緭鍑恒€俓n\n缁间笂鎵€杩帮紝绋嬪簭鏈€缁堜細杈撳嚭瀛楃 'B'銆俓n\n棰樼洰涓殑闄堣堪鏄€滃垪绋嬪簭杈撳嚭鐨勬槸 A鈥濄€傜敱浜庣▼搴忓疄闄呰緭鍑虹殑鏄?'B'锛屾墍浠ヨ繖涓檲杩版槸閿欒鐨勩€?,
        "explanationText": "璁╂垜浠€愯鍒嗘瀽杩欐 C++ 浠ｇ爜锛?1. char x = 65; * 杩欒浠ｇ爜澹版槑浜嗕竴涓瓧绗﹀瀷鍙橀噺 x锛屽苟灏嗗叾鍒濆鍖栦负鏁存暟鍊?65銆?* 鍦?ASCII 缂栫爜涓紝鏁存暟 65 瀵瑰簲鐨勫瓧绗︽槸 'A'銆傛墍浠ワ紝姝ゆ椂 x 鐨勫€间负 'A'銆?2. x++; * 杩欒浠ｇ爜瀵瑰彉閲?x 鎵ц浜嗗悗缃嚜澧炴搷浣溿€?* x 鐨勫€间粠 'A' (ASCII 65) 澧炲姞 1锛屽彉涓?'B' (ASCII 66)銆?* 姝ゆ椂锛寈 鐨勫€间负 'B'銆?3. cout << x++ << endl; * 杩欒浠ｇ爜灏?x 鐨勫€艰緭鍑哄埌鎺у埗鍙帮紝鐒跺悗鎹㈣銆?* 杩欓噷鐨?x++ 涔熸槸涓€涓悗缃嚜澧炴搷浣滅銆傚畠鐨勮涓烘槸锛?* 棣栧厛锛屼娇鐢?x 鐨勫綋鍓嶅€艰繘琛岃緭鍑恒€?* 鐒跺悗锛屽湪杈撳嚭瀹屾垚鍚庯紝x 鐨勫€煎啀鑷 1銆?* 鍦ㄦ墽琛屽埌杩欒鏃讹紝x 鐨勫綋鍓嶅€兼槸 'B' (ASCII 66)銆?* 鎵€浠ワ紝cout 浼氳緭鍑哄瓧绗?'B'銆?* 杈撳嚭瀹屾垚鍚庯紝x 鐨勫€间細浠?'B' (ASCII 66) 鑷鍒?'C' (ASCII 67)銆備絾杩欎釜 'C' 涓嶄細鍦ㄨ繖琛屼唬鐮佷腑琚緭鍑恒€?缁间笂鎵€杩帮紝绋嬪簭鏈€缁堜細杈撳嚭瀛楃 'B'銆?棰樼洰涓殑闄堣堪鏄€滃垪绋嬪簭杈撳嚭鐨勬槸 A鈥濄€傜敱浜庣▼搴忓疄闄呰緭鍑虹殑鏄?'B'锛屾墍浠ヨ繖涓檲杩版槸閿欒鐨勩€?,
        "levelTag": "gesp3",
        "options": [],
        "reviewStatus": "reviewed",
        "stem": "鍒楃▼搴忚緭鍑虹殑鏄?A 銆傦紙 锛塡n```cpp\nchar x=65;\nx++;\ncout<<x++<<endl;\n\n```",
        "stemText": "鍒楃▼搴忚緭鍑虹殑鏄?A 銆傦紙 锛?cpp char x=65; x++; cout<<x++<<endl;",
        "tags": [
          "椤哄簭缁撴瀯"
        ],
        "type": "judge",
        "updatedAt": "2026-03-23T14:13:09.409Z"
      }
    },
    {
      "_id": "69c52eeed215db96b03c34b8",
      "questionUid": "gesp-2025-03-cpp-1-q22",
      "adminNote": "",
      "detail": "",
      "issueType": "wrong_answer",
      "levelTag": "gesp1",
      "paperQuestionNo": 22,
      "reportedAt": "2026-03-26T13:04:46.031Z",
      "reporterName": "鍏冩緢",
      "source": "gesp",
      "sourceDocId": 279,
      "sourceTitle": "GESP-C++-2025骞?鏈堜竴绾х湡棰樺嵎GESP-C++-2025骞?鏈堜竴绾х湡棰樺嵎",
      "status": "pending",
      "tags": [
        "鏉′欢缁撴瀯"
      ],
      "type": "judge",
      "question": {
        "_id": "69bf4dd3d215db96b0027491",
        "questionUid": "gesp-2025-03-cpp-1-q22",
        "answer": "true",
        "enabled": true,
        "explanation": "棰樼洰瑕佹眰鍒ゆ柇缁欏畾鐨?C++ 浠ｇ爜鎵ц鍚庢槸鍚︿細杈撳嚭 7 涓?`true`銆傛垜浠潵閫愪竴鍒嗘瀽寰幆涓?`i` 鐨勫€间互鍙婂搴旂殑鏉′欢琛ㄨ揪寮?`(i * 2 < i * i)` 鐨勭粨鏋溿€俓n\n寰幆 `for (int i = 0; i < 10; i++)` 浼氫娇 `i` 浠?0 閬嶅巻鍒?9銆俓n\n1.  褰?`i = 0` 鏃讹細\n    琛ㄨ揪寮忎负 `(0 * 2 < 0 * 0)`锛屽嵆 `(0 < 0)`锛岀粨鏋滀负 `false`銆俓n2.  褰?`i = 1` 鏃讹細\n    琛ㄨ揪寮忎负 `(1 * 2 < 1 * 1)`锛屽嵆 `(2 < 1)`锛岀粨鏋滀负 `false`銆俓n3.  褰?`i = 2` 鏃讹細\n    琛ㄨ揪寮忎负 `(2 * 2 < 2 * 2)`锛屽嵆 `(4 < 4)`锛岀粨鏋滀负 `false`銆俓n4.  褰?`i = 3` 鏃讹細\n    琛ㄨ揪寮忎负 `(3 * 2 < 3 * 3)`锛屽嵆 `(6 < 9)`锛岀粨鏋滀负 `true`銆俓n5.  褰?`i = 4` 鏃讹細\n    琛ㄨ揪寮忎负 `(4 * 2 < 4 * 4)`锛屽嵆 `(8 < 16)`锛岀粨鏋滀负 `true`銆俓n6.  褰?`i = 5` 鏃讹細\n    琛ㄨ揪寮忎负 `(5 * 2 < 5 * 5)`锛屽嵆 `(10 < 25)`锛岀粨鏋滀负 `true`銆俓n7.  褰?`i = 6` 鏃讹細\n    琛ㄨ揪寮忎负 `(6 * 2 < 6 * 6)`锛屽嵆 `(12 < 36)`锛岀粨鏋滀负 `true`銆俓n8.  褰?`i = 7` 鏃讹細\n    琛ㄨ揪寮忎负 `(7 * 2 < 7 * 7)`锛屽嵆 `(14 < 49)`锛岀粨鏋滀负 `true`銆俓n9.  褰?`i = 8` 鏃讹細\n    琛ㄨ揪寮忎负 `(8 * 2 < 8 * 8)`锛屽嵆 `(16 < 64)`锛岀粨鏋滀负 `true`銆俓n10. 褰?`i = 9` 鏃讹細\n    琛ㄨ揪寮忎负 `(9 * 2 < 9 * 9)`锛屽嵆 `(18 < 81)`锛岀粨鏋滀负 `true`銆俓n\n杈撳嚭缁撴灉灏嗘槸锛歚false false false true true true true true true true `\n\n缁熻杈撳嚭鐨?`true` 鐨勬暟閲忥細浠?`i = 3` 鍒?`i = 9`锛屾€诲叡鏈?7 涓?`true`銆俓n\n鍥犳锛屼唬鐮佹墽琛屽悗纭疄浼氳緭鍑?7 涓?`true`銆傞鐩腑鐨勬弿杩版槸姝ｇ‘鐨勩€?,
        "explanationText": "棰樼洰瑕佹眰鍒ゆ柇缁欏畾鐨?C++ 浠ｇ爜鎵ц鍚庢槸鍚︿細杈撳嚭 7 涓?true銆傛垜浠潵閫愪竴鍒嗘瀽寰幆涓?i 鐨勫€间互鍙婂搴旂殑鏉′欢琛ㄨ揪寮?(i * 2 < i * i) 鐨勭粨鏋溿€?寰幆 for (int i = 0; i < 10; i++) 浼氫娇 i 浠?0 閬嶅巻鍒?9銆?1. 褰?i = 0 鏃讹細 琛ㄨ揪寮忎负 (0 * 2 < 0 * 0)锛屽嵆 (0 < 0)锛岀粨鏋滀负 false銆?2. 褰?i = 1 鏃讹細 琛ㄨ揪寮忎负 (1 * 2 < 1 * 1)锛屽嵆 (2 < 1)锛岀粨鏋滀负 false銆?3. 褰?i = 2 鏃讹細 琛ㄨ揪寮忎负 (2 * 2 < 2 * 2)锛屽嵆 (4 < 4)锛岀粨鏋滀负 false銆?4. 褰?i = 3 鏃讹細 琛ㄨ揪寮忎负 (3 * 2 < 3 * 3)锛屽嵆 (6 < 9)锛岀粨鏋滀负 true銆?5. 褰?i = 4 鏃讹細 琛ㄨ揪寮忎负 (4 * 2 < 4 * 4)锛屽嵆 (8 < 16)锛岀粨鏋滀负 true銆?6. 褰?i = 5 鏃讹細 琛ㄨ揪寮忎负 (5 * 2 < 5 * 5)锛屽嵆 (10 < 25)锛岀粨鏋滀负 true銆?7. 褰?i = 6 鏃讹細 琛ㄨ揪寮忎负 (6 * 2 < 6 * 6)锛屽嵆 (12 < 36)锛岀粨鏋滀负 true銆?8. 褰?i = 7 鏃讹細 琛ㄨ揪寮忎负 (7 * 2 < 7 * 7)锛屽嵆 (14 < 49)锛岀粨鏋滀负 true銆?9. 褰?i = 8 鏃讹細 琛ㄨ揪寮忎负 (8 * 2 < 8 * 8)锛屽嵆 (16 < 64)锛岀粨鏋滀负 true銆?10. 褰?i = 9 鏃讹細 琛ㄨ揪寮忎负 (9 * 2 < 9 * 9)锛屽嵆 (18 < 81)锛岀粨鏋滀负 true銆?杈撳嚭缁撴灉灏嗘槸锛歠alse false false true true true true true true true 缁熻杈撳嚭鐨?true 鐨勬暟閲忥細浠?i = 3 鍒?i = 9锛屾€诲叡鏈?7 涓?true銆?鍥犳锛屼唬鐮佹墽琛屽悗纭疄浼氳緭鍑?7 涓?true銆傞鐩腑鐨勬弿杩版槸姝ｇ‘鐨勩€?,
        "levelTag": "gesp1",
        "options": [
          {
            "key": "true",
            "text": "",
            "textPlain": "",
            "images": []
          },
          {
            "key": "false",
            "text": "",
            "textPlain": "",
            "images": []
          }
        ],
        "reviewStatus": "pending",
        "stem": "涓嬮潰鐨?C++ 浠ｇ爜鎵ц鍚庡皢鍏堝悗杈撳嚭 7 涓?true銆傦紙 锛塡n```cpp\nfor (int i = 0; i < 10; i++)\n    cout << (i * 2 < i * i) << \" \";\n```",
        "stemText": "涓嬮潰鐨?C++ 浠ｇ爜鎵ц鍚庡皢鍏堝悗杈撳嚭 7 涓?true銆傦紙 锛?cpp for (int i = 0; i < 10; i++) cout << (i * 2 < i * i) << \" \";",
        "tags": [
          "鏉′欢缁撴瀯"
        ],
        "type": "judge",
        "updatedAt": "2026-03-26T13:29:24.344Z"
      }
    },
    {
      "_id": "69c529a0d215db96b03be92d",
      "questionUid": "gesp-2024-09-cpp-1-q4",
      "adminNote": "",
      "detail": "",
      "issueType": "wrong_answer",
      "levelTag": "gesp1",
      "paperQuestionNo": 4,
      "reportedAt": "2026-03-26T12:42:08.936Z",
      "reporterName": "鍏冩緢",
      "source": "gesp",
      "sourceDocId": 271,
      "sourceTitle": "GESP-C++-2024骞?鏈堜竴绾х湡棰樺嵎GESP-C++-2024骞?鏈堜竴绾х湡棰樺嵎",
      "status": "pending",
      "tags": [
        "鏁板鍩虹"
      ],
      "type": "single",
      "question": {
        "_id": "69beb5e2d215db96b0fd0329",
        "questionUid": "gesp-2024-09-cpp-1-q4",
        "answer": "",
        "enabled": true,
        "explanation": "",
        "explanationText": "",
        "levelTag": "gesp1",
        "options": [
          {
            "key": "A",
            "text": "14",
            "textPlain": "14",
            "images": []
          },
          {
            "key": "B",
            "text": "4",
            "textPlain": "4",
            "images": []
          },
          {
            "key": "C",
            "text": "1",
            "textPlain": "1",
            "images": []
          },
          {
            "key": "D",
            "text": "0",
            "textPlain": "0",
            "images": []
          }
        ],
        "reviewStatus": "pending",
        "stem": "C++琛ㄨ揪寮?`10 - 3 * 2` 鐨勫€兼槸( )銆?,
        "stemText": "C++琛ㄨ揪寮?10 - 3 * 2 鐨勫€兼槸( )銆?,
        "tags": [
          "鏁板鍩虹"
        ],
        "type": "single",
        "updatedAt": "2026-03-26T13:58:28.993Z"
      }
    },
    {
      "_id": "69c3d7f5d215db96b02e939b",
      "questionUid": "gesp-2024-09-cpp-1-q4",
      "adminNote": "",
      "detail": "娌℃湁绛旀",
      "issueType": "wrong_answer",
      "levelTag": "gesp1",
      "paperQuestionNo": 4,
      "reportedAt": "2026-03-26T11:25:18.828Z",
      "reporterName": "鐜嬫姝?,
      "source": "gesp",
      "sourceDocId": 271,
      "sourceTitle": "GESP-C++-2024骞?鏈堜竴绾х湡棰樺嵎GESP-C++-2024骞?鏈堜竴绾х湡棰樺嵎",
      "status": "pending",
      "tags": [
        "鏁板鍩虹"
      ],
      "type": "single",
      "question": {
        "_id": "69beb5e2d215db96b0fd0329",
        "questionUid": "gesp-2024-09-cpp-1-q4",
        "answer": "",
        "enabled": true,
        "explanation": "",
        "explanationText": "",
        "levelTag": "gesp1",
        "options": [
          {
            "key": "A",
            "text": "14",
            "textPlain": "14",
            "images": []
          },
          {
            "key": "B",
            "text": "4",
            "textPlain": "4",
            "images": []
          },
          {
            "key": "C",
            "text": "1",
            "textPlain": "1",
            "images": []
          },
          {
            "key": "D",
            "text": "0",
            "textPlain": "0",
            "images": []
          }
        ],
        "reviewStatus": "pending",
        "stem": "C++琛ㄨ揪寮?`10 - 3 * 2` 鐨勫€兼槸( )銆?,
        "stemText": "C++琛ㄨ揪寮?10 - 3 * 2 鐨勫€兼槸( )銆?,
        "tags": [
          "鏁板鍩虹"
        ],
        "type": "single",
        "updatedAt": "2026-03-26T13:58:28.993Z"
      }
    },
    {
      "_id": "69c51311d215db96b03ae798",
      "questionUid": "gesp-2024-09-cpp-1-q4",
      "adminNote": "",
      "detail": "娌℃湁瑙ｆ瀽锛屽洓涓瓟妗堥兘涓嶅",
      "issueType": "other",
      "levelTag": "gesp1",
      "paperQuestionNo": 4,
      "reportedAt": "2026-03-26T11:05:53.008Z",
      "reporterName": "瀛欏紜鐒?,
      "source": "gesp",
      "sourceDocId": 271,
      "sourceTitle": "GESP-C++-2024骞?鏈堜竴绾х湡棰樺嵎GESP-C++-2024骞?鏈堜竴绾х湡棰樺嵎",
      "status": "pending",
      "tags": [
        "鏁板鍩虹"
      ],
      "type": "single",
      "question": {
        "_id": "69beb5e2d215db96b0fd0329",
        "questionUid": "gesp-2024-09-cpp-1-q4",
        "answer": "",
        "enabled": true,
        "explanation": "",
        "explanationText": "",
        "levelTag": "gesp1",
        "options": [
          {
            "key": "A",
            "text": "14",
            "textPlain": "14",
            "images": []
          },
          {
            "key": "B",
            "text": "4",
            "textPlain": "4",
            "images": []
          },
          {
            "key": "C",
            "text": "1",
            "textPlain": "1",
            "images": []
          },
          {
            "key": "D",
            "text": "0",
            "textPlain": "0",
            "images": []
          }
        ],
        "reviewStatus": "pending",
        "stem": "C++琛ㄨ揪寮?`10 - 3 * 2` 鐨勫€兼槸( )銆?,
        "stemText": "C++琛ㄨ揪寮?10 - 3 * 2 鐨勫€兼槸( )銆?,
        "tags": [
          "鏁板鍩虹"
        ],
        "type": "single",
        "updatedAt": "2026-03-26T13:58:28.993Z"
      }
    },
    {
      "_id": "69c4f4bfd215db96b039c4f2",
      "questionUid": "gesp-2024-09-cpp-1-q4",
      "adminNote": "",
      "detail": "10-6 涓嶆槸 4 鍚?,
      "issueType": "wrong_answer",
      "levelTag": "gesp1",
      "paperQuestionNo": 4,
      "reportedAt": "2026-03-26T08:56:31.249Z",
      "reporterName": "鑲栨鏋?,
      "source": "gesp",
      "sourceDocId": 271,
      "sourceTitle": "GESP-C++-2024骞?鏈堜竴绾х湡棰樺嵎GESP-C++-2024骞?鏈堜竴绾х湡棰樺嵎",
      "status": "pending",
      "tags": [
        "鏁板鍩虹"
      ],
      "type": "single",
      "question": {
        "_id": "69beb5e2d215db96b0fd0329",
        "questionUid": "gesp-2024-09-cpp-1-q4",
        "answer": "",
        "enabled": true,
        "explanation": "",
        "explanationText": "",
        "levelTag": "gesp1",
        "options": [
          {
            "key": "A",
            "text": "14",
            "textPlain": "14",
            "images": []
          },
          {
            "key": "B",
            "text": "4",
            "textPlain": "4",
            "images": []
          },
          {
            "key": "C",
            "text": "1",
            "textPlain": "1",
            "images": []
          },
          {
            "key": "D",
            "text": "0",
            "textPlain": "0",
            "images": []
          }
        ],
        "reviewStatus": "pending",
        "stem": "C++琛ㄨ揪寮?`10 - 3 * 2` 鐨勫€兼槸( )銆?,
        "stemText": "C++琛ㄨ揪寮?10 - 3 * 2 鐨勫€兼槸( )銆?,
        "tags": [
          "鏁板鍩虹"
        ],
        "type": "single",
        "updatedAt": "2026-03-26T13:58:28.993Z"
      }
    },
    {
      "_id": "69c4e61dd215db96b0390d5f",
      "questionUid": "gesp-2024-12-cpp-3-q20",
      "adminNote": "",
      "detail": "",
      "issueType": "wrong_answer",
      "levelTag": "gesp3",
      "paperQuestionNo": 20,
      "reportedAt": "2026-03-26T07:54:05.762Z",
      "reporterName": "鐜嬫旦瀹?",
      "source": "gesp",
      "sourceDocId": 249,
      "sourceTitle": "GESP-C++-2024骞?2鏈堜笁绾х湡棰樺嵎GESP-C++-2024骞?2鏈堜笁绾х湡棰樺嵎",
      "status": "pending",
      "tags": [
        "GESP",
        "浣嶈繍绠?
      ],
      "type": "judge",
      "question": {
        "_id": "69beb5e2d215db96b0fd04f4",
        "questionUid": "gesp-2024-12-cpp-3-q20",
        "answer": "true",
        "enabled": true,
        "explanation": "1.  `char x=65;`\n    *   杩欎竴琛屽皢瀛楃鍙橀噺 `x` 鍒濆鍖栦负鏁存暟鍊?65銆傚湪 ASCII 缂栫爜涓紝65 瀵瑰簲鐨勫瓧绗︽槸 'A'銆傛墍浠ワ紝姝ゆ椂 `x` 瀛樺偍鐨勬槸瀛楃 'A'銆俓n\n2.  `x=x&00001111;`\n    *   杩欎竴琛屾墽琛屼竴涓綅杩愮畻锛氭寜浣嶄笌锛?锛夈€俓n    *   `x` 鐨勫綋鍓嶅€兼槸 65銆俓n    *   `00001111` 鏄竴涓叓杩涘埗锛坥ctal锛夊瓧闈㈤噺锛屽洜涓烘暟瀛椾互 `0` 寮€澶淬€俓n    *   灏嗗叓杩涘埗 `00001111` 杞崲涓哄崄杩涘埗锛歕n        `00001111` (鍏繘鍒? = `1 * 8^3 + 1 * 8^2 + 1 * 8^1 + 1 * 8^0`\n        = `1 * 512 + 1 * 64 + 1 * 8 + 1 * 1`\n        = `512 + 64 + 8 + 1`\n        = `585` (鍗佽繘鍒?\n    *   鎵€浠ワ紝琛ㄨ揪寮忓疄闄呬笂鏄?`x = 65 & 585;`銆俓n    *   鐜板湪鎴戜滑杩涜鎸変綅涓庢搷浣溿€備负浜嗚繘琛屾寜浣嶄笌锛岄€氬父浼氬皢鎿嶄綔鏁版彁鍗囧埌鑷冲皯 `int` 绫诲瀷銆俓n        *   65 鐨勪簩杩涘埗琛ㄧず锛堝亣璁?32 浣?`int`锛夛細`00000000 00000000 00000000 01000001`\n        *   585 鐨勪簩杩涘埗琛ㄧず锛堝亣璁?32 浣?`int`锛夛細`00000000 00000000 00000010 01001001`\n    *   鎵ц鎸変綅涓庢搷浣滐細\n        ```\n          00000000 00000000 00000000 01000001  (65)\n        & 00000000 00000000 00000010 01001001  (585)\n        -------------------------------------\n          00000000 00000000 00000000 01000001  (65)\n        ```\n    *   鎸変綅涓庣殑缁撴灉鏄?65銆傝繖涓粨鏋?65 琚祴鍊煎洖 `char` 绫诲瀷鐨?`x`銆傜敱浜?65 鍦?`char` 绫诲瀷鐨勮寖鍥村唴锛宍x` 鐨勫€间粛鐒舵槸 65銆俓n\n3.  `cout<<x<<endl;`\n    *   杩欎竴琛屽皢 `x` 鐨勫€艰緭鍑哄埌鎺у埗鍙般€傜敱浜?`x` 鏄?`char` 绫诲瀷锛屽苟涓斿叾鍊间负 65锛宍cout` 浼氬皢鍏惰В閲婁负 ASCII 瀛楃骞舵墦鍗板嚭鏉ャ€俓n    *   ASCII 鐮?65 瀵瑰簲鐨勫瓧绗︽槸 'A'銆俓n\n缁间笂鎵€杩帮紝绋嬪簭鏈€缁堜細杈撳嚭瀛楃 'A'銆傚洜姝わ紝棰樼洰涓殑闄堣堪鈥滀笅鍒楃▼搴忚緭鍑虹殑鏄?`A`鈥濇槸姝ｇ‘鐨勩€俓n\nThe final answer is $\\boxed{T}$",
        "explanationText": "1. char x=65; * 杩欎竴琛屽皢瀛楃鍙橀噺 x 鍒濆鍖栦负鏁存暟鍊?65銆傚湪 ASCII 缂栫爜涓紝65 瀵瑰簲鐨勫瓧绗︽槸 'A'銆傛墍浠ワ紝姝ゆ椂 x 瀛樺偍鐨勬槸瀛楃 'A'銆?2. x=x&00001111; * 杩欎竴琛屾墽琛屼竴涓綅杩愮畻锛氭寜浣嶄笌锛?锛夈€?* x 鐨勫綋鍓嶅€兼槸 65銆?* 00001111 鏄竴涓叓杩涘埗锛坥ctal锛夊瓧闈㈤噺锛屽洜涓烘暟瀛椾互 0 寮€澶淬€?* 灏嗗叓杩涘埗 00001111 杞崲涓哄崄杩涘埗锛?00001111 (鍏繘鍒? = 1 * 8^3 + 1 * 8^2 + 1 * 8^1 + 1 * 8^0 = 1 * 512 + 1 * 64 + 1 * 8 + 1 * 1 = 512 + 64 + 8 + 1 = 585 (鍗佽繘鍒? * 鎵€浠ワ紝琛ㄨ揪寮忓疄闄呬笂鏄?x = 65 & 585;銆?* 鐜板湪鎴戜滑杩涜鎸変綅涓庢搷浣溿€備负浜嗚繘琛屾寜浣嶄笌锛岄€氬父浼氬皢鎿嶄綔鏁版彁鍗囧埌鑷冲皯 int 绫诲瀷銆?* 65 鐨勪簩杩涘埗琛ㄧず锛堝亣璁?32 浣?int锛夛細00000000 00000000 00000000 01000001 * 585 鐨勪簩杩涘埗琛ㄧず锛堝亣璁?32 浣?int锛夛細00000000 00000000 00000010 01001001 * 鎵ц鎸変綅涓庢搷浣滐細 00000000 00000000 00000000 01000001 (65) & 00000000 00000000 00000010 01001001 (585) ------------------------------------- 00000000 00000000 00000000 01000001 (65) * 鎸変綅涓庣殑缁撴灉鏄?65銆傝繖涓粨鏋?65 琚祴鍊煎洖 char 绫诲瀷鐨?x銆傜敱浜?65 鍦?char 绫诲瀷鐨勮寖鍥村唴锛寈 鐨勫€间粛鐒舵槸 65銆?3. cout<<x<<endl; * 杩欎竴琛屽皢 x 鐨勫€艰緭鍑哄埌鎺у埗鍙般€傜敱浜?x 鏄?char 绫诲瀷锛屽苟涓斿叾鍊间负 65锛宑out 浼氬皢鍏惰В閲婁负 ASCII 瀛楃骞舵墦鍗板嚭鏉ャ€?* ASCII 鐮?65 瀵瑰簲鐨勫瓧绗︽槸 'A'銆?缁间笂鎵€杩帮紝绋嬪簭鏈€缁堜細杈撳嚭瀛楃 'A'銆傚洜姝わ紝棰樼洰涓殑闄堣堪鈥滀笅鍒楃▼搴忚緭鍑虹殑鏄?A鈥濇槸姝ｇ‘鐨勩€?The final answer is $\\boxed{T}$",
        "levelTag": "gesp3",
        "options": [],
        "reviewStatus": "reviewed",
        "stem": "涓嬪垪绋嬪簭杈撳嚭鐨勬槸 `A` 锛?锛?\n```cpp\nchar x=65;\nx=x&00001111;\ncout<<x<<endl;\n\n```",
        "stemText": "涓嬪垪绋嬪簭杈撳嚭鐨勬槸 A 锛?锛?cpp char x=65; x=x&00001111; cout<<x<<endl;",
        "tags": [
          "GESP",
          "浣嶈繍绠?
        ],
        "type": "judge",
        "updatedAt": "2026-03-25T09:11:35.983Z"
      }
    },
    {
      "_id": "69c4087fd215db96b030e997",
      "questionUid": "gesp-2023-12-cpp-6-q7",
      "adminNote": "",
      "detail": "瑙ｆ瀽閲岀殑鍝堝か鏇兼爲鏄繖鏍风殑锛歕n(鏍硅妭鐐?11)\n/0 \\1\n(wrd_space:4) (lohe:7)\n/0 \\1 /0 \\1\n(wr:2)(d_space:2) (l:3) (ohe:4)\n/0 \\1 /0 \\1 /0 \\1\n(w:1)(r:1)(d:1)(' ':1) (o:2) (he:2)\n/0 \\1\n(h:1)(e:1)",
      "issueType": "formatting",
      "levelTag": "gesp6",
      "paperQuestionNo": 7,
      "reportedAt": "2026-03-25T16:08:31.997Z",
      "reporterName": "鏉庣汗钀?,
      "source": "gesp",
      "sourceDocId": 233,
      "sourceTitle": "GESP-C++-2023骞?2鏈堝叚绾х湡棰樺嵎GESP-C++-2023骞?2鏈堝叚绾х湡棰樺嵎",
      "status": "pending",
      "tags": [
        "GESP",
        "鎺掑簭"
      ],
      "type": "single",
      "question": {
        "_id": "69beb5e2d215db96b0fd0151",
        "questionUid": "gesp-2023-12-cpp-6-q7",
        "answer": "B",
        "enabled": true,
        "explanation": "闇嶅か鏇肩紪鐮侊紙Huffman Coding锛夋槸涓€绉嶇敤浜庢棤鎹熸暟鎹帇缂╃殑鍙橀暱缂栫爜鏂规硶銆傚畠鐨勬牳蹇冩€濇兂鏄牴鎹瓧绗︾殑棰戠巼鏉ユ瀯寤轰竴涓簩鍙夋爲锛堥湇澶浖鏍戯級锛岄鐜囪秺楂樼殑瀛楃锛屽叾缂栫爜闀垮害瓒婄煭锛涢鐜囪秺浣庣殑瀛楃锛屽叾缂栫爜闀垮害瓒婇暱銆傛渶缁堢洰鏍囨槸浣垮緱鎵€鏈夊瓧绗︾紪鐮佸悗鐨勬€绘瘮鐗规暟鏈€灏戙€俓n\n姝ラ濡備笅锛歕n\n1.  **缁熻瀛楃棰戠巼锛?*\n    棣栧厛锛屾垜浠渶瑕佺粺璁″瓧绗︿覆 \"hello world\" 涓瘡涓瓧绗﹀嚭鐜扮殑棰戠巼銆俓n    瀛楃涓诧細\"h e l l o   w o r l d\" (娉ㄦ剰鏈変竴涓┖鏍?\n    瀛楃 | 棰戠巼\n    -----|-----\n    h    | 1\n    e    | 1\n    l    | 3\n    o    | 2\n    ' '  | 1 (绌烘牸)\n    w    | 1\n    r    | 1\n    d    | 1\n    鎬诲瓧绗︽暟锛? + 1 + 3 + 2 + 1 + 1 + 1 + 1 = 11\n\n2.  **鏋勫缓闇嶅か鏇兼爲锛?*\n    鎴戜滑灏嗘瘡涓瓧绗﹀強鍏堕鐜囪涓轰竴涓妭鐐癸紝鐒跺悗閲嶅浠ヤ笅鎿嶄綔锛岀洿鍒板彧鍓╀笅涓€涓妭鐐癸紙鏍硅妭鐐癸級锛歕n    *   閫夋嫨棰戠巼鏈€灏忕殑涓や釜鑺傜偣銆俓n    *   鍒涘缓涓€涓柊鐨勭埗鑺傜偣锛屽叾棰戠巼鏄繖涓や釜瀛愯妭鐐圭殑棰戠巼涔嬪拰銆俓n    *   灏嗚繖涓や釜瀛愯妭鐐逛粠鍒楄〃涓Щ闄わ紝骞跺皢鏂扮殑鐖惰妭鐐规坊鍔犲埌鍒楄〃涓€俓n\n    鍒濆鑺傜偣锛堟寜棰戠巼鎺掑簭锛夛細\n    (h:1), (e:1), (w:1), (r:1), (d:1), (' ':1), (o:2), (l:3)\n\n    *   **绗?姝ワ細** 鍚堝苟 (h:1) 鍜?(e:1) -> (he:2)\n        鍓╀綑鑺傜偣锛?w:1), (r:1), (d:1), (' ':1), (o:2), (l:3), (he:2)\n        鎺掑簭鍚庯細(w:1), (r:1), (d:1), (' ':1), (o:2), (he:2), (l:3)\n\n    *   **绗?姝ワ細** 鍚堝苟 (w:1) 鍜?(r:1) -> (wr:2)\n        鍓╀綑鑺傜偣锛?d:1), (' ':1), (o:2), (he:2), (l:3), (wr:2)\n        鎺掑簭鍚庯細(d:1), (' ':1), (o:2), (he:2), (wr:2), (l:3)\n\n    *   **绗?姝ワ細** 鍚堝苟 (d:1) 鍜?(' ':1) -> (d_space:2)\n        鍓╀綑鑺傜偣锛?o:2), (he:2), (wr:2), (l:3), (d_space:2)\n        鎺掑簭鍚庯細(o:2), (he:2), (wr:2), (d_space:2), (l:3)\n\n    *   **绗?姝ワ細** 鍚堝苟 (o:2) 鍜?(he:2) -> (ohe:4)\n        鍓╀綑鑺傜偣锛?wr:2), (d_space:2), (l:3), (ohe:4)\n        鎺掑簭鍚庯細(wr:2), (d_space:2), (l:3), (ohe:4)\n\n    *   **绗?姝ワ細** 鍚堝苟 (wr:2) 鍜?(d_space:2) -> (wrd_space:4)\n        鍓╀綑鑺傜偣锛?l:3), (ohe:4), (wrd_space:4)\n        鎺掑簭鍚庯細(l:3), (ohe:4), (wrd_space:4)\n\n    *   **绗?姝ワ細** 鍚堝苟 (l:3) 鍜?(ohe:4) -> (lohe:7)\n        鍓╀綑鑺傜偣锛?wrd_space:4), (lohe:7)\n        鎺掑簭鍚庯細(wrd_space:4), (lohe:7)\n\n    *   **绗?姝ワ細** 鍚堝苟 (wrd_space:4) 鍜?(lohe:7) -> (root:11)\n        鏈€缁堝緱鍒版牴鑺傜偣锛岄鐜囦负11锛堟€诲瓧绗︽暟锛夈€俓n\n3.  **鍒嗛厤闇嶅か鏇肩紪鐮佸苟璁＄畻鎬绘瘮鐗规暟锛?*\n    浠庨湇澶浖鏍戠殑鏍硅妭鐐瑰紑濮嬶紝鍚戝乏鍒嗘敮鍒嗛厤 '0'锛屽悜鍙冲垎鏀垎閰?'1'銆傚埌杈惧彾瀛愯妭鐐规椂锛岃矾寰勪笂鐨?'0' 鍜?'1' 搴忓垪灏辨槸璇ュ瓧绗︾殑闇嶅か鏇肩紪鐮併€俓n\n    鏍规嵁涓婅堪鏋勫缓杩囩▼锛屼竴绉嶅彲鑳界殑闇嶅か鏇兼爲鍜岀紪鐮佸涓嬶細\n    (鏍硅妭鐐?11)\n      /0         \\1\n    (wrd_space:4) (lohe:7)\n      /0 \\1         /0 \\1\n    (wr:2)(d_space:2) (l:3) (ohe:4)\n    /0 \\1 /0 \\1           /0 \\1\n    (w:1)(r:1)(d:1)(' ':1) (o:2) (he:2)\n                               /0 \\1\n                              (h:1)(e:1)\n\n    瀛楃 | 棰戠巼 | 闇嶅か鏇肩紪鐮?| 缂栫爜闀垮害\n    -----|------|------------|---------\n    w    | 1    | 000        | 3\n    r    | 1    | 001        | 3\n    d    | 1    | 010        | 3\n    ' '  | 1    | 011        | 3\n    l    | 3    | 10         | 2\n    o    | 2    | 110        | 3\n    h    | 1    | 1110       | 4\n    e    | 1    | 1111       | 4\n\n    璁＄畻鎬绘瘮鐗规暟 = 危 (瀛楃棰戠巼 脳 缂栫爜闀垮害)\n    鎬绘瘮鐗规暟 = (1 * 3) + (1 * 3) + (1 * 3) + (1 * 3) + (3 * 2) + (2 * 3) + (1 * 4) + (1 * 4)\n    鎬绘瘮鐗规暟 = 3 + 3 + 3 + 3 + 6 + 6 + 4 + 4\n    鎬绘瘮鐗规暟 = 12 + 12 + 8\n    鎬绘瘮鐗规暟 = 32\n\n    鍗充娇鍦ㄦ瀯寤洪湇澶浖鏍戞椂锛岀敱浜庨鐜囩浉鍚岀殑鑺傜偣鍚堝苟椤哄簭涓嶅悓锛屽彲鑳藉鑷村叿浣撶殑缂栫爜鏈夋墍涓嶅悓锛屼絾鏈€缁堢殑鎬绘瘮鐗规暟锛堝姞鏉冭矾寰勯暱搴︿箣鍜岋級灏嗘槸鐩稿悓鐨勬渶灏忓€笺€俓n\n鍥犳锛屽 \"hello world\" 浣跨敤闇嶅か鏇肩紪鐮侊紝鏈€灏戦渶瑕?32 姣旂壒銆俓n\nThe final answer is $\\boxed{B}$",
        "explanationText": "闇嶅か鏇肩紪鐮侊紙Huffman Coding锛夋槸涓€绉嶇敤浜庢棤鎹熸暟鎹帇缂╃殑鍙橀暱缂栫爜鏂规硶銆傚畠鐨勬牳蹇冩€濇兂鏄牴鎹瓧绗︾殑棰戠巼鏉ユ瀯寤轰竴涓簩鍙夋爲锛堥湇澶浖鏍戯級锛岄鐜囪秺楂樼殑瀛楃锛屽叾缂栫爜闀垮害瓒婄煭锛涢鐜囪秺浣庣殑瀛楃锛屽叾缂栫爜闀垮害瓒婇暱銆傛渶缁堢洰鏍囨槸浣垮緱鎵€鏈夊瓧绗︾紪鐮佸悗鐨勬€绘瘮鐗规暟鏈€灏戙€?姝ラ濡備笅锛?1. 缁熻瀛楃棰戠巼锛?棣栧厛锛屾垜浠渶瑕佺粺璁″瓧绗︿覆 \"hello world\" 涓瘡涓瓧绗﹀嚭鐜扮殑棰戠巼銆?瀛楃涓诧細\"h e l l o w o r l d\" (娉ㄦ剰鏈変竴涓┖鏍? 瀛楃 | 棰戠巼 -----|----- h | 1 e | 1 l | 3 o | 2 ' ' | 1 (绌烘牸) w | 1 r | 1 d | 1 鎬诲瓧绗︽暟锛? + 1 + 3 + 2 + 1 + 1 + 1 + 1 = 11 2. 鏋勫缓闇嶅か鏇兼爲锛?鎴戜滑灏嗘瘡涓瓧绗﹀強鍏堕鐜囪涓轰竴涓妭鐐癸紝鐒跺悗閲嶅浠ヤ笅鎿嶄綔锛岀洿鍒板彧鍓╀笅涓€涓妭鐐癸紙鏍硅妭鐐癸級锛?* 閫夋嫨棰戠巼鏈€灏忕殑涓や釜鑺傜偣銆?* 鍒涘缓涓€涓柊鐨勭埗鑺傜偣锛屽叾棰戠巼鏄繖涓や釜瀛愯妭鐐圭殑棰戠巼涔嬪拰銆?* 灏嗚繖涓や釜瀛愯妭鐐逛粠鍒楄〃涓Щ闄わ紝骞跺皢鏂扮殑鐖惰妭鐐规坊鍔犲埌鍒楄〃涓€?鍒濆鑺傜偣锛堟寜棰戠巼鎺掑簭锛夛細 (h:1), (e:1), (w:1), (r:1), (d:1), (' ':1), (o:2), (l:3) * 绗?姝ワ細 鍚堝苟 (h:1) 鍜?(e:1) -> (he:2) 鍓╀綑鑺傜偣锛?w:1), (r:1), (d:1), (' ':1), (o:2), (l:3), (he:2) 鎺掑簭鍚庯細(w:1), (r:1), (d:1), (' ':1), (o:2), (he:2), (l:3) * 绗?姝ワ細 鍚堝苟 (w:1) 鍜?(r:1) -> (wr:2) 鍓╀綑鑺傜偣锛?d:1), (' ':1), (o:2), (he:2), (l:3), (wr:2) 鎺掑簭鍚庯細(d:1), (' ':1), (o:2), (he:2), (wr:2), (l:3) * 绗?姝ワ細 鍚堝苟 (d:1) 鍜?(' ':1) -> (dspace:2) 鍓╀綑鑺傜偣锛?o:2), (he:2), (wr:2), (l:3), (dspace:2) 鎺掑簭鍚庯細(o:2), (he:2), (wr:2), (dspace:2), (l:3) * 绗?姝ワ細 鍚堝苟 (o:2) 鍜?(he:2) -> (ohe:4) 鍓╀綑鑺傜偣锛?wr:2), (dspace:2), (l:3), (ohe:4) 鎺掑簭鍚庯細(wr:2), (dspace:2), (l:3), (ohe:4) * 绗?姝ワ細 鍚堝苟 (wr:2) 鍜?(dspace:2) -> (wrdspace:4) 鍓╀綑鑺傜偣锛?l:3), (ohe:4), (wrdspace:4) 鎺掑簭鍚庯細(l:3), (ohe:4), (wrdspace:4) * 绗?姝ワ細 鍚堝苟 (l:3) 鍜?(ohe:4) -> (lohe:7) 鍓╀綑鑺傜偣锛?wrdspace:4), (lohe:7) 鎺掑簭鍚庯細(wrdspace:4), (lohe:7) * 绗?姝ワ細 鍚堝苟 (wrdspace:4) 鍜?(lohe:7) -> (root:11) 鏈€缁堝緱鍒版牴鑺傜偣锛岄鐜囦负11锛堟€诲瓧绗︽暟锛夈€?3. 鍒嗛厤闇嶅か鏇肩紪鐮佸苟璁＄畻鎬绘瘮鐗规暟锛?浠庨湇澶浖鏍戠殑鏍硅妭鐐瑰紑濮嬶紝鍚戝乏鍒嗘敮鍒嗛厤 '0'锛屽悜鍙冲垎鏀垎閰?'1'銆傚埌杈惧彾瀛愯妭鐐规椂锛岃矾寰勪笂鐨?'0' 鍜?'1' 搴忓垪灏辨槸璇ュ瓧绗︾殑闇嶅か鏇肩紪鐮併€?鏍规嵁涓婅堪鏋勫缓杩囩▼锛屼竴绉嶅彲鑳界殑闇嶅か鏇兼爲鍜岀紪鐮佸涓嬶細 (鏍硅妭鐐?11) /0 \\1 (wrdspace:4) (lohe:7) /0 \\1 /0 \\1 (wr:2)(dspace:2) (l:3) (ohe:4) /0 \\1 /0 \\1 /0 \\1 (w:1)(r:1)(d:1)(' ':1) (o:2) (he:2) /0 \\1 (h:1)(e:1) 瀛楃 | 棰戠巼 | 闇嶅か鏇肩紪鐮?| 缂栫爜闀垮害 -----|------|------------|--------- w | 1 | 000 | 3 r | 1 | 001 | 3 d | 1 | 010 | 3 ' ' | 1 | 011 | 3 l | 3 | 10 | 2 o | 2 | 110 | 3 h | 1 | 1110 | 4 e | 1 | 1111 | 4 璁＄畻鎬绘瘮鐗规暟 = 危 (瀛楃棰戠巼 脳 缂栫爜闀垮害) 鎬绘瘮鐗规暟 = (1 * 3) + (1 * 3) + (1 * 3) + (1 * 3) + (3 * 2) + (2 * 3) + (1 * 4) + (1 * 4) 鎬绘瘮鐗规暟 = 3 + 3 + 3 + 3 + 6 + 6 + 4 + 4 鎬绘瘮鐗规暟 = 12 + 12 + 8 鎬绘瘮鐗规暟 = 32 鍗充娇鍦ㄦ瀯寤洪湇澶浖鏍戞椂锛岀敱浜庨鐜囩浉鍚岀殑鑺傜偣鍚堝苟椤哄簭涓嶅悓锛屽彲鑳藉鑷村叿浣撶殑缂栫爜鏈夋墍涓嶅悓锛屼絾鏈€缁堢殑鎬绘瘮鐗规暟锛堝姞鏉冭矾寰勯暱搴︿箣鍜岋級灏嗘槸鐩稿悓鐨勬渶灏忓€笺€?鍥犳锛屽 \"hello world\" 浣跨敤闇嶅か鏇肩紪鐮侊紝鏈€灏戦渶瑕?32 姣旂壒銆?The final answer is $\\boxed{B}$",
        "levelTag": "gesp6",
        "options": [
          {
            "key": "A",
            "text": "4",
            "textPlain": "4",
            "images": []
          },
          {
            "key": "B",
            "text": "32",
            "textPlain": "32",
            "images": []
          },
          {
            "key": "C",
            "text": "64",
            "textPlain": "64",
            "images": []
          },
          {
            "key": "D",
            "text": "88",
            "textPlain": "88",
            "images": []
          }
        ],
        "reviewStatus": "pending",
        "stem": "瀵?$hello$ $world$ 浣跨敤闇嶅か鏇肩紪鐮侊紙 $Huffman$ $Coding$ 锛夛紝鏈€灏?$bit$ 锛堟瘮鐗癸級涓猴紙 锛夈€?,
        "stemText": "瀵?$hello$ $world$ 浣跨敤闇嶅か鏇肩紪鐮侊紙 $Huffman$ $Coding$ 锛夛紝鏈€灏?$bit$ 锛堟瘮鐗癸級涓猴紙 锛夈€?,
        "tags": [
          "GESP",
          "鎺掑簭"
        ],
        "type": "single",
        "updatedAt": "2026-03-25T16:07:27.102Z"
      }
    },
    {
      "_id": "69c3ef2cd215db96b02ffbf0",
      "questionUid": "downloads-1102-q18",
      "adminNote": "",
      "detail": "",
      "issueType": "wrong_answer",
      "levelTag": "gesp2",
      "paperQuestionNo": 18,
      "reportedAt": "2026-03-25T14:20:28.713Z",
      "reporterName": "闄堜繆璞?,
      "source": "downloads",
      "sourceDocId": 1102,
      "sourceTitle": "1102 - GESP 浜岀骇鏍烽锛圕++ 缁勶級",
      "status": "pending",
      "tags": [
        "downloads-import",
        "objective",
        "gesp",
        "sample",
        "椤哄簭缁撴瀯"
      ],
      "type": "judge",
      "question": {
        "_id": "69c0b260d215db96b0110a97",
        "questionUid": "downloads-1102-q18",
        "answer": "B",
        "enabled": true,
        "explanation": "鍦?C++ 缂栫▼涓紝娉ㄩ噴鏄啓缁欑▼搴忓憳鐪嬬殑锛岀敤浜庤В閲婁唬鐮佺殑鍔熻兘鍜岄€昏緫锛屾彁楂樹唬鐮佺殑鍙鎬с€俓n\n1. 缂栬瘧杩囩▼锛氬綋缂栬瘧鍣紙濡?g++锛夌紪璇戞簮浠ｇ爜鏃讹紝绗竴姝ラ澶勭悊闃舵灏变細灏嗘墍鏈夌殑娉ㄩ噴鍒犻櫎銆俓n2. 杩愯鏁堢巼锛氱敱浜庣紪璇戝櫒鍦ㄧ敓鎴愭渶缁堢殑鍙墽琛屾枃浠讹紙鏈哄櫒鐮侊級涔嬪墠宸茬粡鍘绘帀浜嗘敞閲婏紝鍥犳娉ㄩ噴涓嶄細鍗犵敤浠讳綍杩愯鏃剁殑鍐呭瓨锛屼篃涓嶄細鎵ц浠讳綍鎸囦护銆俓n3. 缁撹锛氭棤璁轰唬鐮佷腑鍐欎簡澶氬皯娉ㄩ噴锛岄兘涓嶄細瀵圭▼搴忕殑杩愯閫熷害浜х敓浠讳綍褰卞搷銆傚敮涓€鍙兘浜х敓鐨勫井灏忓奖鍝嶆槸缂栬瘧婧愪唬鐮佺殑鏃堕棿浼氱◢寰鍔犱竴鐐圭偣锛堝洜涓虹紪璇戝櫒闇€瑕佹壂鎻忓苟璺宠繃杩欎簺鏂囧瓧锛夛紝浣嗚繖鍦ㄥ疄闄呭紑鍙戜腑鏄彲浠ュ拷鐣ヤ笉璁＄殑銆俓n\n鍥犳锛岄鐩腑璇粹€滄敞閲婁細鎷栨參绋嬪簭杩愯閫熷害鈥濇槸閿欒鐨勩€?,
        "explanationText": "鍦?C++ 缂栫▼涓紝娉ㄩ噴鏄啓缁欑▼搴忓憳鐪嬬殑锛岀敤浜庤В閲婁唬鐮佺殑鍔熻兘鍜岄€昏緫锛屾彁楂樹唬鐮佺殑鍙鎬с€?1. 缂栬瘧杩囩▼锛氬綋缂栬瘧鍣紙濡?g++锛夌紪璇戞簮浠ｇ爜鏃讹紝绗竴姝ラ澶勭悊闃舵灏变細灏嗘墍鏈夌殑娉ㄩ噴鍒犻櫎銆?2. 杩愯鏁堢巼锛氱敱浜庣紪璇戝櫒鍦ㄧ敓鎴愭渶缁堢殑鍙墽琛屾枃浠讹紙鏈哄櫒鐮侊級涔嬪墠宸茬粡鍘绘帀浜嗘敞閲婏紝鍥犳娉ㄩ噴涓嶄細鍗犵敤浠讳綍杩愯鏃剁殑鍐呭瓨锛屼篃涓嶄細鎵ц浠讳綍鎸囦护銆?3. 缁撹锛氭棤璁轰唬鐮佷腑鍐欎簡澶氬皯娉ㄩ噴锛岄兘涓嶄細瀵圭▼搴忕殑杩愯閫熷害浜х敓浠讳綍褰卞搷銆傚敮涓€鍙兘浜х敓鐨勫井灏忓奖鍝嶆槸缂栬瘧婧愪唬鐮佺殑鏃堕棿浼氱◢寰鍔犱竴鐐圭偣锛堝洜涓虹紪璇戝櫒闇€瑕佹壂鎻忓苟璺宠繃杩欎簺鏂囧瓧锛夛紝浣嗚繖鍦ㄥ疄闄呭紑鍙戜腑鏄彲浠ュ拷鐣ヤ笉璁＄殑銆?鍥犳锛岄鐩腑璇粹€滄敞閲婁細鎷栨參绋嬪簭杩愯閫熷害鈥濇槸閿欒鐨勩€?,
        "levelTag": "gesp2",
        "options": [
          {
            "key": "A",
            "text": "姝ｇ‘",
            "textPlain": "姝ｇ‘",
            "images": []
          },
          {
            "key": "B",
            "text": "閿欒",
            "textPlain": "閿欒",
            "images": []
          }
        ],
        "reviewStatus": "pending",
        "stem": "C++ 璇█涓紝娉ㄩ噴铏界劧寰堟湁鐢紝浣嗕笉鑳藉啓澶锛屽惁鍒欎細鎷栨參绋嬪簭杩愯閫熷害銆傦紙 锛?,
        "stemText": "C++ 璇█涓紝娉ㄩ噴铏界劧寰堟湁鐢紝浣嗕笉鑳藉啓澶锛屽惁鍒欎細鎷栨參绋嬪簭杩愯閫熷害銆傦紙 锛?,
        "tags": [
          "downloads-import",
          "objective",
          "gesp",
          "sample",
          "椤哄簭缁撴瀯"
        ],
        "type": "judge",
        "updatedAt": "2026-03-25T14:18:17.884Z"
      }
    },
    {
      "_id": "69c3eaf4d215db96b02fb82a",
      "questionUid": "downloads-1015-q19",
      "adminNote": "",
      "detail": "娌℃湁绋嬪簭娈?,
      "issueType": "other",
      "levelTag": "gesp4",
      "paperQuestionNo": 19,
      "reportedAt": "2026-03-25T14:02:28.827Z",
      "reporterName": "鑲栨鏋?,
      "source": "downloads",
      "sourceDocId": 1015,
      "sourceTitle": "1015 - NOIP 2014 鏅強缁勫垵璧涜瘯棰?,
      "status": "pending",
      "tags": [
        "downloads-import",
        "objective",
        "noip",
        "beginner",
        "寰幆缁撴瀯",
        "妯℃嫙"
      ],
      "type": "single",
      "question": {
        "_id": "69c0b260d215db96b01108e1",
        "questionUid": "downloads-1015-q19",
        "answer": "B",
        "enabled": true,
        "explanation": "铏界劧棰樼洰鎻忚堪涓己澶变簡鍏蜂綋鐨勭▼搴忔浠ｇ爜锛屼絾鏍规嵁 GESP/CSP 绛夌紪绋嬭€冪骇涓绫婚鐩殑鍏稿瀷鍘熷瀷锛岃绋嬪簭娈甸€氬父濡備笅锛歕ns = a;\nfor (b = 1; b <= c; b++)\n    s = s + 1;\n\n瀵硅绋嬪簭娈佃繘琛岄€昏緫鍒嗘瀽锛歕n1. 鍒濆鐘舵€侊細鍙橀噺 s 琚祴鍊间负 a銆俓n2. 寰幆杩囩▼锛氬惊鐜彉閲?b 浠?1 寮€濮嬶紝姣忔閫掑 1锛岀洿鍒拌揪鍒?c銆傚洜涓洪鐩凡鐭?c > 0锛屾墍浠ュ惊鐜綋浼氭墽琛?c 娆°€俓n3. 绱姞鎿嶄綔锛氬湪姣忔寰幆涓紝s 鐨勫€奸兘浼氬鍔?1銆俓n4. 鏈€缁堢粨鏋滐細s 鐨勫垵濮嬪€兼槸 a锛岀粡杩?c 娆♀€滃姞 1鈥濈殑鎿嶄綔鍚庯紝s 鐨勬渶缁堝€肩瓑浜?a + c銆俓n\n鍥犳锛屾暣涓▼搴忔瀹炵幇鐨勫姛鑳藉氨鏄皢 a 涓?c 鐨勫拰璁＄畻鍑烘潵骞惰祴鍊肩粰 s锛岀瓑浠风殑璧嬪€艰鍙ユ槸 s = a + c銆傞€夐」 B 姝ｇ‘銆?,
        "explanationText": "铏界劧棰樼洰鎻忚堪涓己澶变簡鍏蜂綋鐨勭▼搴忔浠ｇ爜锛屼絾鏍规嵁 GESP/CSP 绛夌紪绋嬭€冪骇涓绫婚鐩殑鍏稿瀷鍘熷瀷锛岃绋嬪簭娈甸€氬父濡備笅锛?s = a; for (b = 1; b <= c; b++) s = s + 1; 瀵硅绋嬪簭娈佃繘琛岄€昏緫鍒嗘瀽锛?1. 鍒濆鐘舵€侊細鍙橀噺 s 琚祴鍊间负 a銆?2. 寰幆杩囩▼锛氬惊鐜彉閲?b 浠?1 寮€濮嬶紝姣忔閫掑 1锛岀洿鍒拌揪鍒?c銆傚洜涓洪鐩凡鐭?c > 0锛屾墍浠ュ惊鐜綋浼氭墽琛?c 娆°€?3. 绱姞鎿嶄綔锛氬湪姣忔寰幆涓紝s 鐨勫€奸兘浼氬鍔?1銆?4. 鏈€缁堢粨鏋滐細s 鐨勫垵濮嬪€兼槸 a锛岀粡杩?c 娆♀€滃姞 1鈥濈殑鎿嶄綔鍚庯紝s 鐨勬渶缁堝€肩瓑浜?a + c銆?鍥犳锛屾暣涓▼搴忔瀹炵幇鐨勫姛鑳藉氨鏄皢 a 涓?c 鐨勫拰璁＄畻鍑烘潵骞惰祴鍊肩粰 s锛岀瓑浠风殑璧嬪€艰鍙ユ槸 s = a + c銆傞€夐」 B 姝ｇ‘銆?,
        "levelTag": "gesp4",
        "options": [
          {
            "key": "A",
            "text": "s = a + b",
            "textPlain": "s = a + b",
            "images": []
          },
          {
            "key": "B",
            "text": "s = a + c",
            "textPlain": "s = a + c",
            "images": []
          },
          {
            "key": "C",
            "text": "s = s + c",
            "textPlain": "s = s + c",
            "images": []
          },
          {
            "key": "D",
            "text": "s = b + c",
            "textPlain": "s = b + c",
            "images": []
          }
        ],
        "reviewStatus": "pending",
        "stem": "鑻ユ湁濡備笅绋嬪簭娈碉紝鍏朵腑s,a,b,c鍧囧凡瀹氫箟涓烘暣鍨嬪彉閲忥紝涓攁,c鍧囧凡璧嬪€硷紝c>0銆?鍒欎笌涓婅堪绋嬪簭娈靛姛鑳界瓑浠风殑璧嬪€艰鍙ユ槸锛?锛?,
        "stemText": "鑻ユ湁濡備笅绋嬪簭娈碉紝鍏朵腑s,a,b,c鍧囧凡瀹氫箟涓烘暣鍨嬪彉閲忥紝涓攁,c鍧囧凡璧嬪€硷紝c>0銆?鍒欎笌涓婅堪绋嬪簭娈靛姛鑳界瓑浠风殑璧嬪€艰鍙ユ槸锛?锛?,
        "tags": [
          "downloads-import",
          "objective",
          "noip",
          "beginner",
          "寰幆缁撴瀯",
          "妯℃嫙"
        ],
        "type": "single",
        "updatedAt": "2026-03-23T03:59:56.841Z"
      }
    },
    {
      "_id": "69c3e87ad215db96b02f9511",
      "questionUid": "gesp-2024-09-cpp-1-q4",
      "adminNote": "",
      "detail": "娌℃湁姝ｇ‘鐨勯€夐」鍟?,
      "issueType": "wrong_options",
      "levelTag": "gesp1",
      "paperQuestionNo": 4,
      "reportedAt": "2026-03-25T13:51:54.186Z",
      "reporterName": "钁ｈ嚧杩?,
      "source": "gesp",
      "sourceDocId": 271,
      "sourceTitle": "GESP-C++-2024骞?鏈堜竴绾х湡棰樺嵎GESP-C++-2024骞?鏈堜竴绾х湡棰樺嵎",
      "status": "pending",
      "tags": [
        "鏁板鍩虹"
      ],
      "type": "single",
      "question": {
        "_id": "69beb5e2d215db96b0fd0329",
        "questionUid": "gesp-2024-09-cpp-1-q4",
        "answer": "",
        "enabled": true,
        "explanation": "",
        "explanationText": "",
        "levelTag": "gesp1",
        "options": [
          {
            "key": "A",
            "text": "14",
            "textPlain": "14",
            "images": []
          },
          {
            "key": "B",
            "text": "4",
            "textPlain": "4",
            "images": []
          },
          {
            "key": "C",
            "text": "1",
            "textPlain": "1",
            "images": []
          },
          {
            "key": "D",
            "text": "0",
            "textPlain": "0",
            "images": []
          }
        ],
        "reviewStatus": "pending",
        "stem": "C++琛ㄨ揪寮?`10 - 3 * 2` 鐨勫€兼槸( )銆?,
        "stemText": "C++琛ㄨ揪寮?10 - 3 * 2 鐨勫€兼槸( )銆?,
        "tags": [
          "鏁板鍩虹"
        ],
        "type": "single",
        "updatedAt": "2026-03-26T13:58:28.993Z"
      }
    },
    {
      "_id": "69c3e708d215db96b02f81e9",
      "questionUid": "gesp-2024-09-cpp-1-q4",
      "adminNote": "",
      "detail": "閫変粈涔堥兘涓嶅",
      "issueType": "wrong_answer",
      "levelTag": "gesp1",
      "paperQuestionNo": 4,
      "reportedAt": "2026-03-25T13:45:44.070Z",
      "reporterName": "闄堜繆璞?,
      "source": "gesp",
      "sourceDocId": 271,
      "sourceTitle": "GESP-C++-2024骞?鏈堜竴绾х湡棰樺嵎GESP-C++-2024骞?鏈堜竴绾х湡棰樺嵎",
      "status": "pending",
      "tags": [
        "鏁板鍩虹"
      ],
      "type": "single",
      "question": {
        "_id": "69beb5e2d215db96b0fd0329",
        "questionUid": "gesp-2024-09-cpp-1-q4",
        "answer": "",
        "enabled": true,
        "explanation": "",
        "explanationText": "",
        "levelTag": "gesp1",
        "options": [
          {
            "key": "A",
            "text": "14",
            "textPlain": "14",
            "images": []
          },
          {
            "key": "B",
            "text": "4",
            "textPlain": "4",
            "images": []
          },
          {
            "key": "C",
            "text": "1",
            "textPlain": "1",
            "images": []
          },
          {
            "key": "D",
            "text": "0",
            "textPlain": "0",
            "images": []
          }
        ],
        "reviewStatus": "pending",
        "stem": "C++琛ㄨ揪寮?`10 - 3 * 2` 鐨勫€兼槸( )銆?,
        "stemText": "C++琛ㄨ揪寮?10 - 3 * 2 鐨勫€兼槸( )銆?,
        "tags": [
          "鏁板鍩虹"
        ],
        "type": "single",
        "updatedAt": "2026-03-26T13:58:28.993Z"
      }
    },
    {
      "_id": "69c3ddbfd215db96b02ef092",
      "questionUid": "downloads-1104-q23",
      "adminNote": "",
      "detail": "",
      "issueType": "wrong_answer",
      "levelTag": "gesp4",
      "paperQuestionNo": 23,
      "reportedAt": "2026-03-25T13:06:07.116Z",
      "reporterName": "鏉庝紵姣?,
      "source": "downloads",
      "sourceDocId": 1104,
      "sourceTitle": "1104 - GESP 鍥涚骇鏍烽锛圕++ 缁勶級",
      "status": "pending",
      "tags": [
        "downloads-import",
        "objective",
        "gesp",
        "sample",
        "椤哄簭缁撴瀯"
      ],
      "type": "judge",
      "question": {
        "_id": "69c0b260d215db96b0110ace",
        "questionUid": "downloads-1104-q23",
        "answer": "B",
        "enabled": true,
        "explanation": "鍦?C++ 缂栫▼璇█涓細\n1. & 鏄湁鏁堢殑杩愮畻绗︼紝鍙互鐢ㄤ綔鎸変綅涓庯紙Bitwise AND锛夎繍绠楃锛屼篃鍙互鐢ㄤ綔鍙栧湴鍧€杩愮畻绗︺€俓n2. && 鏄湁鏁堢殑杩愮畻绗︼紝鐢ㄤ綔閫昏緫涓庯紙Logical AND锛夎繍绠楃銆俓n3. * 鏄湁鏁堢殑杩愮畻绗︼紝鍙互鐢ㄤ綔涔樻硶杩愮畻绗︼紝涔熷彲浠ョ敤浣滆В寮曠敤锛圖ereference锛夎繍绠楃锛堣闂寚閽堟寚鍚戠殑鍐呭锛夈€俓n4. ** 涓嶆槸 C++ 涓殑杩愮畻绗︺€傝櫧鐒跺湪澶勭悊浜岀骇鎸囬拡鏃跺彲浠ヨ繛缁啓涓や釜鏄熷彿锛堜緥濡?**p锛夛紝浣嗚繖瀹為檯涓婃槸涓ゆ浣跨敤浜嗚В寮曠敤杩愮畻绗?*锛岃€屼笉鏄竴涓悕涓?** 鐨勭嫭绔嬭繍绠楃銆傚湪鏌愪簺鍏朵粬缂栫▼璇█锛堝 Python锛変腑锛?* 鏄箓杩愮畻绗︼紝浣嗗湪 C++ 涓苟娌℃湁杩欎釜杩愮畻绗︼紙C++ 鐨勫箓杩愮畻闇€瑕佷娇鐢?math.h 鎴?cmath 搴撲腑鐨?pow() 鍑芥暟锛夈€俓n\n鍥犳锛岄鐩腑璇?** 涔熸槸 C++ 杩愮畻绗︽槸涓嶆纭殑銆?,
        "explanationText": "鍦?C++ 缂栫▼璇█涓細 1. & 鏄湁鏁堢殑杩愮畻绗︼紝鍙互鐢ㄤ綔鎸変綅涓庯紙Bitwise AND锛夎繍绠楃锛屼篃鍙互鐢ㄤ綔鍙栧湴鍧€杩愮畻绗︺€?2. && 鏄湁鏁堢殑杩愮畻绗︼紝鐢ㄤ綔閫昏緫涓庯紙Logical AND锛夎繍绠楃銆?3. * 鏄湁鏁堢殑杩愮畻绗︼紝鍙互鐢ㄤ綔涔樻硶杩愮畻绗︼紝涔熷彲浠ョ敤浣滆В寮曠敤锛圖ereference锛夎繍绠楃锛堣闂寚閽堟寚鍚戠殑鍐呭锛夈€?4. 涓嶆槸 C++ 涓殑杩愮畻绗︺€傝櫧鐒跺湪澶勭悊浜岀骇鎸囬拡鏃跺彲浠ヨ繛缁啓涓や釜鏄熷彿锛堜緥濡?p锛夛紝浣嗚繖瀹為檯涓婃槸涓ゆ浣跨敤浜嗚В寮曠敤杩愮畻绗?锛岃€屼笉鏄竴涓悕涓?鐨勭嫭绔嬭繍绠楃銆傚湪鏌愪簺鍏朵粬缂栫▼璇█锛堝 Python锛変腑锛?鏄箓杩愮畻绗︼紝浣嗗湪 C++ 涓苟娌℃湁杩欎釜杩愮畻绗︼紙C++ 鐨勫箓杩愮畻闇€瑕佷娇鐢?math.h 鎴?cmath 搴撲腑鐨?pow() 鍑芥暟锛夈€?鍥犳锛岄鐩腑璇?* 涔熸槸 C++ 杩愮畻绗︽槸涓嶆纭殑銆?,
        "levelTag": "gesp4",
        "options": [
          {
            "key": "A",
            "text": "姝ｇ‘",
            "textPlain": "姝ｇ‘",
            "images": []
          },
          {
            "key": "B",
            "text": "閿欒",
            "textPlain": "閿欒",
            "images": []
          }
        ],
        "reviewStatus": "pending",
        "stem": "& 鍜?&& 閮芥槸 C++ 璇█鐨勮繍绠楃锛? 鍜?** 涔熼兘鏄€傦紙 锛?,
        "stemText": "& 鍜?&& 閮芥槸 C++ 璇█鐨勮繍绠楃锛? 鍜?** 涔熼兘鏄€傦紙 锛?,
        "tags": [
          "downloads-import",
          "objective",
          "gesp",
          "sample",
          "椤哄簭缁撴瀯"
        ],
        "type": "judge",
        "updatedAt": "2026-03-25T13:05:59.805Z"
      }
    },
    {
      "_id": "69c3daa2d215db96b02ebba4",
      "questionUid": "gesp-2024-03-cpp-1-q11",
      "adminNote": "",
      "detail": "",
      "issueType": "wrong_options",
      "levelTag": "gesp1",
      "paperQuestionNo": 11,
      "reportedAt": "2026-03-25T12:52:50.919Z",
      "reporterName": "鐜嬩繚璇楄埅66",
      "source": "gesp",
      "sourceDocId": 255,
      "sourceTitle": "GESP-C++-2024骞?鏈堜竴绾х湡棰樺嵎GESP-C++-2024骞?鏈堜竴绾х湡棰樺嵎",
      "status": "pending",
      "tags": [
        "GESP"
      ],
      "type": "single",
      "question": {
        "_id": "69beb5e2d215db96b0fd01a1",
        "questionUid": "gesp-2024-03-cpp-1-q11",
        "answer": "D",
        "enabled": true,
        "explanation": "鏈鑰冨療C/C++璇█涓暣鍨嬪彉閲忕殑璧嬪€间互鍙婄被鍨嬭浆鎹㈢殑璇硶銆俓n\n鎴戜滑閫愪竴鍒嗘瀽姣忎釜閫夐」锛歕n\nA. `x=(3.16);`\n   杩欐槸涓€涓悎娉曠殑璧嬪€艰鍙ャ€傚湪C/C++涓紝褰撳皢涓€涓诞鐐规暟锛堝`3.16`锛夎祴鍊肩粰涓€涓暣鍨嬪彉閲忔椂锛屼細鍙戠敓闅愬紡绫诲瀷杞崲銆傛诞鐐规暟鐨勬暣鏁伴儴鍒嗕細琚繚鐣欙紝灏忔暟閮ㄥ垎浼氳鎴柇銆傛嫭鍙峰湪杩欓噷鍙槸鏀瑰彉浜嗚〃杈惧紡鐨勪紭鍏堢骇锛屼絾瀵逛簬鍗曚釜瀛楅潰閲廯3.16`鏉ヨ锛屾病鏈夊疄闄呬綔鐢紝瀹冪瓑鍚屼簬`x=3.16;`銆傛墍浠ワ紝杩欎釜璇彞鏄娉曟纭殑銆俓n\nB. `x=3.16;`\n   杩欎篃鏄竴涓悎娉曠殑璧嬪€艰鍙ャ€備笌A閫夐」鐩稿悓锛屽畠浼氬彂鐢熼殣寮忕被鍨嬭浆鎹紝灏嗘诞鐐规暟`3.16`鎴柇涓烘暣鏁癭3`锛岀劧鍚庤祴鍊肩粰`x`銆傝繖涓鍙ユ槸璇硶姝ｇ‘鐨勩€俓n\nC. `x=int(3.16);`\n   杩欐槸涓€涓悎娉曠殑璧嬪€艰鍙ャ€俙int(3.16)`鏄疌++椋庢牸鐨勬樉寮忕被鍨嬭浆鎹紙涔熺О涓哄嚱鏁板紡绫诲瀷杞崲鎴朇++椋庢牸鐨勫己鍒剁被鍨嬭浆鎹級銆傚畠灏嗘诞鐐规暟`3.16`鏄惧紡鍦拌浆鎹负鏁村瀷`3`锛岀劧鍚庤祴鍊肩粰`x`銆傝繖涓鍙ユ槸璇硶姝ｇ‘鐨勩€俓n\nD. `x=3.16 int;`\n   杩欎釜璇彞鏄娉曢敊璇殑銆傚湪C/C++涓紝娌℃湁`3.16 int`杩欐牱鐨勮娉曠粨鏋勬潵琛ㄧず绫诲瀷杞崲鎴栦换浣曞叾浠栨搷浣溿€傜被鍨嬭浆鎹㈤€氬父鍐欏湪瑕佽浆鎹㈢殑鍊间箣鍓嶏紙濡侰椋庢牸鐨刞(int)3.16`鎴朇++椋庢牸鐨刞int(3.16)`锛夛紝鎴栬€呴€氳繃璧嬪€兼椂鐨勯殣寮忚浆鎹㈠畬鎴愩€傚皢绫诲瀷鍚嶆斁鍦ㄦ暟鍊煎悗闈㈡槸鏃犳晥鐨勮娉曘€傜紪璇戝櫒浼氭姤鍛婅娉曢敊璇€俓n\n缁间笂鎵€杩帮紝閫夐」D鐨勮祴鍊艰鍙ユ槸璇硶涓嶆纭殑銆?,
        "explanationText": "鏈鑰冨療C/C++璇█涓暣鍨嬪彉閲忕殑璧嬪€间互鍙婄被鍨嬭浆鎹㈢殑璇硶銆?鎴戜滑閫愪竴鍒嗘瀽姣忎釜閫夐」锛?A. x=(3.16); 杩欐槸涓€涓悎娉曠殑璧嬪€艰鍙ャ€傚湪C/C++涓紝褰撳皢涓€涓诞鐐规暟锛堝3.16锛夎祴鍊肩粰涓€涓暣鍨嬪彉閲忔椂锛屼細鍙戠敓闅愬紡绫诲瀷杞崲銆傛诞鐐规暟鐨勬暣鏁伴儴鍒嗕細琚繚鐣欙紝灏忔暟閮ㄥ垎浼氳鎴柇銆傛嫭鍙峰湪杩欓噷鍙槸鏀瑰彉浜嗚〃杈惧紡鐨勪紭鍏堢骇锛屼絾瀵逛簬鍗曚釜瀛楅潰閲?.16鏉ヨ锛屾病鏈夊疄闄呬綔鐢紝瀹冪瓑鍚屼簬x=3.16;銆傛墍浠ワ紝杩欎釜璇彞鏄娉曟纭殑銆?B. x=3.16; 杩欎篃鏄竴涓悎娉曠殑璧嬪€艰鍙ャ€備笌A閫夐」鐩稿悓锛屽畠浼氬彂鐢熼殣寮忕被鍨嬭浆鎹紝灏嗘诞鐐规暟3.16鎴柇涓烘暣鏁?锛岀劧鍚庤祴鍊肩粰x銆傝繖涓鍙ユ槸璇硶姝ｇ‘鐨勩€?C. x=int(3.16); 杩欐槸涓€涓悎娉曠殑璧嬪€艰鍙ャ€俰nt(3.16)鏄疌++椋庢牸鐨勬樉寮忕被鍨嬭浆鎹紙涔熺О涓哄嚱鏁板紡绫诲瀷杞崲鎴朇++椋庢牸鐨勫己鍒剁被鍨嬭浆鎹級銆傚畠灏嗘诞鐐规暟3.16鏄惧紡鍦拌浆鎹负鏁村瀷3锛岀劧鍚庤祴鍊肩粰x銆傝繖涓鍙ユ槸璇硶姝ｇ‘鐨勩€?D. x=3.16 int; 杩欎釜璇彞鏄娉曢敊璇殑銆傚湪C/C++涓紝娌℃湁3.16 int杩欐牱鐨勮娉曠粨鏋勬潵琛ㄧず绫诲瀷杞崲鎴栦换浣曞叾浠栨搷浣溿€傜被鍨嬭浆鎹㈤€氬父鍐欏湪瑕佽浆鎹㈢殑鍊间箣鍓嶏紙濡侰椋庢牸鐨?int)3.16鎴朇++椋庢牸鐨刬nt(3.16)锛夛紝鎴栬€呴€氳繃璧嬪€兼椂鐨勯殣寮忚浆鎹㈠畬鎴愩€傚皢绫诲瀷鍚嶆斁鍦ㄦ暟鍊煎悗闈㈡槸鏃犳晥鐨勮娉曘€傜紪璇戝櫒浼氭姤鍛婅娉曢敊璇€?缁间笂鎵€杩帮紝閫夐」D鐨勮祴鍊艰鍙ユ槸璇硶涓嶆纭殑銆?,
        "levelTag": "gesp1",
        "options": [
          {
            "key": "A",
            "text": "x=(3.16);",
            "textPlain": "x=(3.16);",
            "images": []
          },
          {
            "key": "B",
            "text": "x=3.16;",
            "textPlain": "x=3.16;",
            "images": []
          },
          {
            "key": "C",
            "text": "x=int(3.16);",
            "textPlain": "x=int(3.16);",
            "images": []
          },
          {
            "key": "D",
            "text": "x=3.16 int;",
            "textPlain": "x=3.16 int;",
            "images": []
          }
        ],
        "reviewStatus": "pending",
        "stem": "涓嬧警鍏充簬鏁村瀷鍙橀噺`int x`鐨勮祴鍊艰鍙ヤ笉姝ｇ‘鏄? )銆?,
        "stemText": "涓嬧警鍏充簬鏁村瀷鍙橀噺int x鐨勮祴鍊艰鍙ヤ笉姝ｇ‘鏄? )銆?,
        "tags": [
          "GESP"
        ],
        "type": "single",
        "updatedAt": "2026-03-26T13:13:18.144Z"
      }
    },
    {
      "_id": "69c3d741d215db96b02e88b4",
      "questionUid": "gesp-2024-09-cpp-3-q20",
      "adminNote": "",
      "detail": "娌?鏈?閫?椤?,
      "issueType": "wrong_options",
      "levelTag": "gesp3",
      "paperQuestionNo": 20,
      "reportedAt": "2026-03-25T12:38:25.797Z",
      "reporterName": "鐜嬫姝?,
      "source": "gesp",
      "sourceDocId": 273,
      "sourceTitle": "GESP-C++-2024骞?鏈堜笁绾х湡棰樺嵎GESP-C++-2024骞?鏈堜笁绾х湡棰樺嵎",
      "status": "pending",
      "tags": [
        "椤哄簭缁撴瀯"
      ],
      "type": "judge",
      "question": {
        "_id": "69beb5e2d215db96b0fd036a",
        "questionUid": "gesp-2024-09-cpp-3-q20",
        "answer": "false",
        "enabled": true,
        "explanation": "璁╂垜浠€愯鍒嗘瀽杩欐 C++ 浠ｇ爜锛歕n\n1.  `char x = 65;`\n    *   杩欒浠ｇ爜澹版槑浜嗕竴涓瓧绗﹀瀷鍙橀噺 `x`锛屽苟灏嗗叾鍒濆鍖栦负鏁存暟鍊?`65`銆俓n    *   鍦?ASCII 缂栫爜涓紝鏁存暟 `65` 瀵瑰簲鐨勫瓧绗︽槸 'A'銆傛墍浠ワ紝姝ゆ椂 `x` 鐨勫€间负 'A'銆俓n\n2.  `x++;`\n    *   杩欒浠ｇ爜瀵瑰彉閲?`x` 鎵ц浜嗗悗缃嚜澧炴搷浣溿€俓n    *   `x` 鐨勫€间粠 'A' (ASCII 65) 澧炲姞 1锛屽彉涓?'B' (ASCII 66)銆俓n    *   姝ゆ椂锛宍x` 鐨勫€间负 'B'銆俓n\n3.  `cout << x++ << endl;`\n    *   杩欒浠ｇ爜灏?`x` 鐨勫€艰緭鍑哄埌鎺у埗鍙帮紝鐒跺悗鎹㈣銆俓n    *   杩欓噷鐨?`x++` 涔熸槸涓€涓悗缃嚜澧炴搷浣滅銆傚畠鐨勮涓烘槸锛歕n        *   棣栧厛锛屼娇鐢?`x` 鐨勫綋鍓嶅€艰繘琛岃緭鍑恒€俓n        *   鐒跺悗锛屽湪杈撳嚭瀹屾垚鍚庯紝`x` 鐨勫€煎啀鑷 1銆俓n    *   鍦ㄦ墽琛屽埌杩欒鏃讹紝`x` 鐨勫綋鍓嶅€兼槸 'B' (ASCII 66)銆俓n    *   鎵€浠ワ紝`cout` 浼氳緭鍑哄瓧绗?'B'銆俓n    *   杈撳嚭瀹屾垚鍚庯紝`x` 鐨勫€间細浠?'B' (ASCII 66) 鑷鍒?'C' (ASCII 67)銆備絾杩欎釜 'C' 涓嶄細鍦ㄨ繖琛屼唬鐮佷腑琚緭鍑恒€俓n\n缁间笂鎵€杩帮紝绋嬪簭鏈€缁堜細杈撳嚭瀛楃 'B'銆俓n\n棰樼洰涓殑闄堣堪鏄€滃垪绋嬪簭杈撳嚭鐨勬槸 A鈥濄€傜敱浜庣▼搴忓疄闄呰緭鍑虹殑鏄?'B'锛屾墍浠ヨ繖涓檲杩版槸閿欒鐨勩€?,
        "explanationText": "璁╂垜浠€愯鍒嗘瀽杩欐 C++ 浠ｇ爜锛?1. char x = 65; * 杩欒浠ｇ爜澹版槑浜嗕竴涓瓧绗﹀瀷鍙橀噺 x锛屽苟灏嗗叾鍒濆鍖栦负鏁存暟鍊?65銆?* 鍦?ASCII 缂栫爜涓紝鏁存暟 65 瀵瑰簲鐨勫瓧绗︽槸 'A'銆傛墍浠ワ紝姝ゆ椂 x 鐨勫€间负 'A'銆?2. x++; * 杩欒浠ｇ爜瀵瑰彉閲?x 鎵ц浜嗗悗缃嚜澧炴搷浣溿€?* x 鐨勫€间粠 'A' (ASCII 65) 澧炲姞 1锛屽彉涓?'B' (ASCII 66)銆?* 姝ゆ椂锛寈 鐨勫€间负 'B'銆?3. cout << x++ << endl; * 杩欒浠ｇ爜灏?x 鐨勫€艰緭鍑哄埌鎺у埗鍙帮紝鐒跺悗鎹㈣銆?* 杩欓噷鐨?x++ 涔熸槸涓€涓悗缃嚜澧炴搷浣滅銆傚畠鐨勮涓烘槸锛?* 棣栧厛锛屼娇鐢?x 鐨勫綋鍓嶅€艰繘琛岃緭鍑恒€?* 鐒跺悗锛屽湪杈撳嚭瀹屾垚鍚庯紝x 鐨勫€煎啀鑷 1銆?* 鍦ㄦ墽琛屽埌杩欒鏃讹紝x 鐨勫綋鍓嶅€兼槸 'B' (ASCII 66)銆?* 鎵€浠ワ紝cout 浼氳緭鍑哄瓧绗?'B'銆?* 杈撳嚭瀹屾垚鍚庯紝x 鐨勫€间細浠?'B' (ASCII 66) 鑷鍒?'C' (ASCII 67)銆備絾杩欎釜 'C' 涓嶄細鍦ㄨ繖琛屼唬鐮佷腑琚緭鍑恒€?缁间笂鎵€杩帮紝绋嬪簭鏈€缁堜細杈撳嚭瀛楃 'B'銆?棰樼洰涓殑闄堣堪鏄€滃垪绋嬪簭杈撳嚭鐨勬槸 A鈥濄€傜敱浜庣▼搴忓疄闄呰緭鍑虹殑鏄?'B'锛屾墍浠ヨ繖涓檲杩版槸閿欒鐨勩€?,
        "levelTag": "gesp3",
        "options": [],
        "reviewStatus": "reviewed",
        "stem": "鍒楃▼搴忚緭鍑虹殑鏄?A 銆傦紙 锛塡n```cpp\nchar x=65;\nx++;\ncout<<x++<<endl;\n\n```",
        "stemText": "鍒楃▼搴忚緭鍑虹殑鏄?A 銆傦紙 锛?cpp char x=65; x++; cout<<x++<<endl;",
        "tags": [
          "椤哄簭缁撴瀯"
        ],
        "type": "judge",
        "updatedAt": "2026-03-23T14:13:09.409Z"
      }
    },
    {
      "_id": "69c3d0b3d215db96b02e345d",
      "questionUid": "gesp-2024-03-cpp-3-q21",
      "adminNote": "",
      "detail": "娌￠€夐」",
      "issueType": "wrong_options",
      "levelTag": "gesp3",
      "paperQuestionNo": 21,
      "reportedAt": "2026-03-25T12:10:27.692Z",
      "reporterName": "榛勫湥娑?,
      "source": "gesp",
      "sourceDocId": 257,
      "sourceTitle": "GESP-C++-2024骞?鏈堜笁绾х湡棰樺嵎GESP-C++-2024骞?鏈堜笁绾х湡棰樺嵎",
      "status": "pending",
      "tags": [
        "GESP"
      ],
      "type": "judge",
      "question": {
        "_id": "69beb5e2d215db96b0fd01de",
        "questionUid": "gesp-2024-03-cpp-3-q21",
        "answer": "true",
        "enabled": true,
        "explanation": "杩欐C++浠ｇ爜浣跨敤浜哷std::string`鐨刞find`鏂规硶鏉ユ煡鎵惧瓙瀛楃涓叉垨瀛楃鍦ㄥ瓧绗︿覆涓涓€娆″嚭鐜扮殑浣嶇疆銆俓n\n1.  `string str=\"gEsP is Interesting\";`锛氬畾涔変簡涓€涓瓧绗︿覆鍙橀噺`str`锛屽叾鍊间负 \"gEsP is Interesting\"銆俓n2.  `int x = str.find(\"s\");`锛氳皟鐢╜str`鐨刞find`鏂规硶锛屾煡鎵惧瓧绗?'s' 鍦ㄥ瓧绗︿覆涓涓€娆″嚭鐜扮殑浣嶇疆銆俓n    *   瀛楃涓?\"gEsP is Interesting\" 鐨勭储寮曚粠0寮€濮嬶細\n        *   g (0)\n        *   E (1)\n        *   s (2)\n        *   P (3)\n        *   (绌烘牸) (4)\n        *   i (5)\n        *   s (6)\n        *   ...\n    *   绗竴涓皬鍐欏瓧姣?'s' 鍑虹幇鍦ㄧ储寮曚负 2 鐨勪綅缃€俓n    *   鍥犳锛屽彉閲?`x` 鐨勫€煎皢鏄?2銆俓n3.  `cout << x << endl;`锛氬皢鍙橀噺 `x` 鐨勫€艰緭鍑哄埌鎺у埗鍙帮紝鐒跺悗鎹㈣銆傜敱浜?`x` 鐨勫€间负 2锛屾墍浠ヤ細杈撳嚭 `2`銆俓n4.  `cout << endl;`锛氬啀娆¤緭鍑轰竴涓崲琛岀銆俓n\n鏍规嵁涓婅堪鍒嗘瀽锛屼唬鐮佺殑杈撳嚭纭疄鏄?`2`銆傛墍浠ラ鐩腑鐨勮娉曟槸姝ｇ‘鐨勩€?,
        "explanationText": "杩欐C++浠ｇ爜浣跨敤浜唖td::string鐨刦ind鏂规硶鏉ユ煡鎵惧瓙瀛楃涓叉垨瀛楃鍦ㄥ瓧绗︿覆涓涓€娆″嚭鐜扮殑浣嶇疆銆?1. string str=\"gEsP is Interesting\";锛氬畾涔変簡涓€涓瓧绗︿覆鍙橀噺str锛屽叾鍊间负 \"gEsP is Interesting\"銆?2. int x = str.find(\"s\");锛氳皟鐢╯tr鐨刦ind鏂规硶锛屾煡鎵惧瓧绗?'s' 鍦ㄥ瓧绗︿覆涓涓€娆″嚭鐜扮殑浣嶇疆銆?* 瀛楃涓?\"gEsP is Interesting\" 鐨勭储寮曚粠0寮€濮嬶細 * g (0) * E (1) * s (2) * P (3) * (绌烘牸) (4) * i (5) * s (6) * ... * 绗竴涓皬鍐欏瓧姣?'s' 鍑虹幇鍦ㄧ储寮曚负 2 鐨勪綅缃€?* 鍥犳锛屽彉閲?x 鐨勫€煎皢鏄?2銆?3. cout << x << endl;锛氬皢鍙橀噺 x 鐨勫€艰緭鍑哄埌鎺у埗鍙帮紝鐒跺悗鎹㈣銆傜敱浜?x 鐨勫€间负 2锛屾墍浠ヤ細杈撳嚭 2銆?4. cout << endl;锛氬啀娆¤緭鍑轰竴涓崲琛岀銆?鏍规嵁涓婅堪鍒嗘瀽锛屼唬鐮佺殑杈撳嚭纭疄鏄?2銆傛墍浠ラ鐩腑鐨勮娉曟槸姝ｇ‘鐨勩€?,
        "levelTag": "gesp3",
        "options": [],
        "reviewStatus": "reviewed",
        "stem": "鎵р緩涓嬧警C++浠ｇ爜鍚庡皢杈撳嚭 `2` 銆?锛?锛塡n```cpp\nint main()\n{\n  string str=\"gEsP is Interesting\";\n  int x = str.find(\"s\");\n  cout << x << endl;\n  cout << endl;\n  return 0;\n}\n\n```",
        "stemText": "鎵р緩涓嬧警C++浠ｇ爜鍚庡皢杈撳嚭 2 銆?锛?锛?cpp int main() { string str=\"gEsP is Interesting\"; int x = str.find(\"s\"); cout << x << endl; cout << endl; return 0; }",
        "tags": [
          "GESP"
        ],
        "type": "judge",
        "updatedAt": "2026-03-23T14:22:44.679Z"
      }
    },
    {
      "_id": "69c3c51bd215db96b02dbfa4",
      "questionUid": "gesp-2024-12-cpp-1-q3",
      "adminNote": "",
      "detail": "",
      "issueType": "wrong_answer",
      "levelTag": "gesp1",
      "paperQuestionNo": 3,
      "reportedAt": "2026-03-25T11:20:59.928Z",
      "reporterName": "鍏冩緢",
      "source": "gesp",
      "sourceDocId": 247,
      "sourceTitle": "GESP-C++-2024骞?2鏈堜竴绾х湡棰樺嵎GESP-C++-2024骞?2鏈堜竴绾х湡棰樺嵎",
      "status": "pending",
      "tags": [
        "GESP"
      ],
      "type": "single",
      "question": {
        "_id": "69beb5e2d215db96b0fd04b5",
        "questionUid": "gesp-2024-12-cpp-1-q3",
        "answer": "A",
        "enabled": true,
        "explanation": "璁╂垜浠€愪竴鍒嗘瀽姣忎釜閫夐」锛歕n\n棰樼洰涓殑浠ｇ爜鏄?`printf(\"Hello,GESP!\");`锛岃繖鏄竴涓娇鐢ㄥ弻寮曞彿 `\"\"` 瀹氫箟鐨勫瓧绗︿覆瀛楅潰閲忋€俓n\nA. 閰嶅鍙屽紩鍙峰唴 锛屼笉鍙互鏈夋眽瀛梊n   - **鍒嗘瀽锛?* 鍦–++锛堜互鍙奀璇█锛変腑锛屽瓧绗︿覆瀛楅潰閲忓彲浠ュ寘鍚换浣曟湁鏁堢殑瀛楃锛屽寘鎷眽瀛椼€傜幇浠++缂栬瘧鍣ㄥ拰鎿嶄綔绯荤粺閫氬父鏀寔Unicode瀛楃闆嗭紙濡俇TF-8锛夛紝鍥犳鍦ㄥ瓧绗︿覆涓娇鐢ㄦ眽瀛楁槸瀹屽叏鍏佽鐨勶紝渚嬪 `printf(\"浣犲ソ锛屼笘鐣?\");` 鏄悎娉曠殑C++浠ｇ爜锛屽苟涓斿湪姝ｇ‘閰嶇疆鐨勭幆澧冧笅鑳藉姝ｅ父杈撳嚭姹夊瓧銆俓n   - **缁撹锛?* 浠嶤++璇█鏍囧噯鍜岀幇浠ｅ疄璺垫潵鐪嬶紝杩欎釜璇存硶鏄?*閿欒**鐨勩€俓n   - **鐒惰€岋紝涓轰粈涔堝畠鍙兘鏄纭瓟妗堬紵** 鍦ㄦ煇浜涚壒瀹氱殑銆佸彈闄愮殑鐜涓紙渚嬪闈炲父鑰佺殑缂栬瘧鍣ㄣ€佷笉鏀寔澶氬瓧鑺傚瓧绗﹂泦鐨勭郴缁熴€佹垨鑰呮煇浜涚珵璧涘钩鍙颁负浜嗛伩鍏嶇紪鐮侀棶棰樿€屽缓璁彧浣跨敤ASCII瀛楃锛夛紝浣跨敤姹夊瓧鍙兘浼氬鑷翠贡鐮佹垨缂栬瘧闂銆傚湪杩欑鐗瑰畾璇涓嬶紝涓轰簡閬垮厤鍏煎鎬ч棶棰橈紝鍙兘浼氭湁鈥滀笉寤鸿浣跨敤姹夊瓧鈥濈敋鑷斥€滀笉鍙互鏈夋眽瀛椻€濈殑璇存硶銆傚鏋滈鐩殣鍚簡杩欑鍙楅檺鐜锛岄偅涔堟閫夐」鍙兘琚涓烘槸姝ｇ‘鐨勩€傚湪鎵€鏈夐€夐」閮藉瓨鍦ㄦ槑鏄鹃棶棰樼殑鎯呭喌涓嬶紝杩欏彲鑳芥槸鍑洪浜烘兂鑰冨療鐨勪竴涓€滅粡楠屾€р€濇垨鈥滅壒瀹氱幆澧冣€濅笅鐨勮鍒欍€俓n\nB. 閰嶅鍙屽紩鍙峰彲浠ョ浉搴旀敼鍙樹负鑻扁絺鍗曞紩鍙封浇杈撳嚭鏁堟灉涓嶅彉\n   - **鍒嗘瀽锛?* 鍦–++涓紝鍗曞紩鍙?`' '` 鐢ㄤ簬琛ㄧず瀛楃瀛楅潰閲忥紙`char` 绫诲瀷锛夛紝鑰屽弻寮曞彿 `\"\"` 鐢ㄤ簬琛ㄧず瀛楃涓插瓧闈㈤噺锛坄const char*` 绫诲瀷锛夈€俙printf` 鍑芥暟鐨勭涓€涓弬鏁版湡鏈涗竴涓瓧绗︿覆锛坄const char*`锛夈€傚鏋滃皢 `printf(\"H\");` 鏀逛负 `printf('H');`锛屽垯浼氬彂鐢熺被鍨嬩笉鍖归厤銆俙'H'` 鏄竴涓瓧绗︼紝鑰屼笉鏄竴涓瓧绗︿覆銆傝繖浼氬鑷寸紪璇戦敊璇垨鏈畾涔夎涓恒€傚嵆浣夸娇鐢?`printf(\"%c\", 'H');` 鏉ユ墦鍗板瓧绗︼紝鍏惰涓轰篃涓庢墦鍗板瓧绗︿覆 `printf(\"H\");` 涓嶅悓锛堝悗鑰呭寘鍚竴涓┖缁堟绗︼級銆俓n   - **缁撹锛?* 杩欎釜璇存硶鏄?*閿欒**鐨勩€俓n\nC. 閰嶅鍙屽紩鍙峰彲浠ョ浉搴旀敼鍙樹负涓変釜杩炵画鑻扁絺鍗曞紩鍙封浇杈撳嚭鏁堟灉涓嶅彉\n   - **鍒嗘瀽锛?* `'''` 杩欐牱鐨勮娉曞湪C++涓笉鏄竴涓湁鏁堢殑瀛楅潰閲忚〃绀烘柟寮忥紝瀹冧細瀵艰嚧缂栬瘧閿欒锛堣娉曢敊璇級銆俓n   - **缁撹锛?* 杩欎釜璇存硶鏄?*閿欒**鐨勩€俓n\nD. 閰嶅鍙屽紩鍙峰彲浠ョ浉搴旀敼鍙樹负涓変釜杩炵画鑻扁絺鍙屽紩鍙封浇杈撳嚭鏁堟灉涓嶅彉\n   - **鍒嗘瀽锛?* `\"\"\"` 杩欐牱鐨勮娉曞湪C++涓篃涓嶆槸涓€涓湁鏁堢殑瀛楅潰閲忚〃绀烘柟寮忥紙铏界劧鍦≒ython绛夊叾浠栬瑷€涓彲鑳界敤浜庡琛屽瓧绗︿覆锛屼絾鍦–++涓細瀵艰嚧缂栬瘧閿欒锛夈€俓n   - **缁撹锛?* 杩欎釜璇存硶鏄?*閿欒**鐨勩€俓n\n**鎬荤粨锛?*\n鏍规嵁C++璇█鏍囧噯锛岄€夐」B銆丆銆丏閮芥槸鏄庣‘閿欒鐨勶紝瀹冧滑娑夊強鍒拌娉曢敊璇垨绫诲瀷涓嶅尮閰嶃€傞€夐」A鍦ㄧ幇浠++鐜涓槸閿欒鐨勶紝鍥犱负瀛楃涓插瓧闈㈤噺鍙互鍖呭惈姹夊瓧銆傜劧鑰岋紝鍦ㄦ煇浜涚壒瀹氱殑銆佸彈闄愮殑缂栫▼鐜鎴栨暀瀛﹁澧冧腑锛屼负浜嗛伩鍏嶇紪鐮佸拰鍏煎鎬ч棶棰橈紝鍙兘浼氭湁鈥滀笉寤鸿鍦ㄥ瓧绗︿覆涓娇鐢ㄦ眽瀛椻€濈敋鑷斥€滀笉鍙互鏈夋眽瀛椻€濈殑璇存硶銆傝€冭檻鍒拌繖鏄竴涓€夋嫨棰橈紝涓擝銆丆銆丏鐨勯敊璇洿涓烘牴鏈拰鏅亶锛屽鏋滃繀椤婚€夋嫨涓€涓€滄纭€濈瓟妗堬紝閭ｄ箞A鍙兘鏄嚭棰樹汉鍩轰簬鏌愮鐗瑰畾鑰冮噺锛堜緥濡傦紝寮鸿皟鍏煎鎬ф垨閬垮厤鍒濆鑰呭彲鑳介亣鍒扮殑缂栫爜闂锛夎€岃瀹氱殑绛旀銆俓n\n鍥犳锛屽湪鎵€鏈夐€夐」閮藉瓨鍦ㄩ棶棰樼殑鎯呭喌涓嬶紝鎴戜滑閫夋嫨A锛屽苟瑙ｉ噴鍏跺彲鑳藉瓨鍦ㄧ殑璇銆俓n\nThe final answer is $\\boxed{A}$",
        "explanationText": "璁╂垜浠€愪竴鍒嗘瀽姣忎釜閫夐」锛?棰樼洰涓殑浠ｇ爜鏄?printf(\"Hello,GESP!\");锛岃繖鏄竴涓娇鐢ㄥ弻寮曞彿 \"\" 瀹氫箟鐨勫瓧绗︿覆瀛楅潰閲忋€?A. 閰嶅鍙屽紩鍙峰唴 锛屼笉鍙互鏈夋眽瀛?- 鍒嗘瀽锛?鍦–++锛堜互鍙奀璇█锛変腑锛屽瓧绗︿覆瀛楅潰閲忓彲浠ュ寘鍚换浣曟湁鏁堢殑瀛楃锛屽寘鎷眽瀛椼€傜幇浠++缂栬瘧鍣ㄥ拰鎿嶄綔绯荤粺閫氬父鏀寔Unicode瀛楃闆嗭紙濡俇TF-8锛夛紝鍥犳鍦ㄥ瓧绗︿覆涓娇鐢ㄦ眽瀛楁槸瀹屽叏鍏佽鐨勶紝渚嬪 printf(\"浣犲ソ锛屼笘鐣?\"); 鏄悎娉曠殑C++浠ｇ爜锛屽苟涓斿湪姝ｇ‘閰嶇疆鐨勭幆澧冧笅鑳藉姝ｅ父杈撳嚭姹夊瓧銆?- 缁撹锛?浠嶤++璇█鏍囧噯鍜岀幇浠ｅ疄璺垫潵鐪嬶紝杩欎釜璇存硶鏄敊璇殑銆?- 鐒惰€岋紝涓轰粈涔堝畠鍙兘鏄纭瓟妗堬紵 鍦ㄦ煇浜涚壒瀹氱殑銆佸彈闄愮殑鐜涓紙渚嬪闈炲父鑰佺殑缂栬瘧鍣ㄣ€佷笉鏀寔澶氬瓧鑺傚瓧绗﹂泦鐨勭郴缁熴€佹垨鑰呮煇浜涚珵璧涘钩鍙颁负浜嗛伩鍏嶇紪鐮侀棶棰樿€屽缓璁彧浣跨敤ASCII瀛楃锛夛紝浣跨敤姹夊瓧鍙兘浼氬鑷翠贡鐮佹垨缂栬瘧闂銆傚湪杩欑鐗瑰畾璇涓嬶紝涓轰簡閬垮厤鍏煎鎬ч棶棰橈紝鍙兘浼氭湁鈥滀笉寤鸿浣跨敤姹夊瓧鈥濈敋鑷斥€滀笉鍙互鏈夋眽瀛椻€濈殑璇存硶銆傚鏋滈鐩殣鍚簡杩欑鍙楅檺鐜锛岄偅涔堟閫夐」鍙兘琚涓烘槸姝ｇ‘鐨勩€傚湪鎵€鏈夐€夐」閮藉瓨鍦ㄦ槑鏄鹃棶棰樼殑鎯呭喌涓嬶紝杩欏彲鑳芥槸鍑洪浜烘兂鑰冨療鐨勪竴涓€滅粡楠屾€р€濇垨鈥滅壒瀹氱幆澧冣€濅笅鐨勮鍒欍€?B. 閰嶅鍙屽紩鍙峰彲浠ョ浉搴旀敼鍙樹负鑻扁絺鍗曞紩鍙封浇杈撳嚭鏁堟灉涓嶅彉 - 鍒嗘瀽锛?鍦–++涓紝鍗曞紩鍙?' ' 鐢ㄤ簬琛ㄧず瀛楃瀛楅潰閲忥紙char 绫诲瀷锛夛紝鑰屽弻寮曞彿 \"\" 鐢ㄤ簬琛ㄧず瀛楃涓插瓧闈㈤噺锛坈onst char 绫诲瀷锛夈€俻rintf 鍑芥暟鐨勭涓€涓弬鏁版湡鏈涗竴涓瓧绗︿覆锛坈onst char锛夈€傚鏋滃皢 printf(\"H\"); 鏀逛负 printf('H');锛屽垯浼氬彂鐢熺被鍨嬩笉鍖归厤銆?H' 鏄竴涓瓧绗︼紝鑰屼笉鏄竴涓瓧绗︿覆銆傝繖浼氬鑷寸紪璇戦敊璇垨鏈畾涔夎涓恒€傚嵆浣夸娇鐢?printf(\"%c\", 'H'); 鏉ユ墦鍗板瓧绗︼紝鍏惰涓轰篃涓庢墦鍗板瓧绗︿覆 printf(\"H\"); 涓嶅悓锛堝悗鑰呭寘鍚竴涓┖缁堟绗︼級銆?- 缁撹锛?杩欎釜璇存硶鏄敊璇殑銆?C. 閰嶅鍙屽紩鍙峰彲浠ョ浉搴旀敼鍙樹负涓変釜杩炵画鑻扁絺鍗曞紩鍙封浇杈撳嚭鏁堟灉涓嶅彉 - 鍒嗘瀽锛?''' 杩欐牱鐨勮娉曞湪C++涓笉鏄竴涓湁鏁堢殑瀛楅潰閲忚〃绀烘柟寮忥紝瀹冧細瀵艰嚧缂栬瘧閿欒锛堣娉曢敊璇級銆?- 缁撹锛?杩欎釜璇存硶鏄敊璇殑銆?D. 閰嶅鍙屽紩鍙峰彲浠ョ浉搴旀敼鍙樹负涓変釜杩炵画鑻扁絺鍙屽紩鍙封浇杈撳嚭鏁堟灉涓嶅彉 - 鍒嗘瀽锛?\"\"\" 杩欐牱鐨勮娉曞湪C++涓篃涓嶆槸涓€涓湁鏁堢殑瀛楅潰閲忚〃绀烘柟寮忥紙铏界劧鍦≒ython绛夊叾浠栬瑷€涓彲鑳界敤浜庡琛屽瓧绗︿覆锛屼絾鍦–++涓細瀵艰嚧缂栬瘧閿欒锛夈€?- 缁撹锛?杩欎釜璇存硶鏄敊璇殑銆?鎬荤粨锛?鏍规嵁C++璇█鏍囧噯锛岄€夐」B銆丆銆丏閮芥槸鏄庣‘閿欒鐨勶紝瀹冧滑娑夊強鍒拌娉曢敊璇垨绫诲瀷涓嶅尮閰嶃€傞€夐」A鍦ㄧ幇浠++鐜涓槸閿欒鐨勶紝鍥犱负瀛楃涓插瓧闈㈤噺鍙互鍖呭惈姹夊瓧銆傜劧鑰岋紝鍦ㄦ煇浜涚壒瀹氱殑銆佸彈闄愮殑缂栫▼鐜鎴栨暀瀛﹁澧冧腑锛屼负浜嗛伩鍏嶇紪鐮佸拰鍏煎鎬ч棶棰橈紝鍙兘浼氭湁鈥滀笉寤鸿鍦ㄥ瓧绗︿覆涓娇鐢ㄦ眽瀛椻€濈敋鑷斥€滀笉鍙互鏈夋眽瀛椻€濈殑璇存硶銆傝€冭檻鍒拌繖鏄竴涓€夋嫨棰橈紝涓擝銆丆銆丏鐨勯敊璇洿涓烘牴鏈拰鏅亶锛屽鏋滃繀椤婚€夋嫨涓€涓€滄纭€濈瓟妗堬紝閭ｄ箞A鍙兘鏄嚭棰樹汉鍩轰簬鏌愮鐗瑰畾鑰冮噺锛堜緥濡傦紝寮鸿皟鍏煎鎬ф垨閬垮厤鍒濆鑰呭彲鑳介亣鍒扮殑缂栫爜闂锛夎€岃瀹氱殑绛旀銆?鍥犳锛屽湪鎵€鏈夐€夐」閮藉瓨鍦ㄩ棶棰樼殑鎯呭喌涓嬶紝鎴戜滑閫夋嫨A锛屽苟瑙ｉ噴鍏跺彲鑳藉瓨鍦ㄧ殑璇銆?The final answer is $\\boxed{A}$",
        "levelTag": "gesp1",
        "options": [
          {
            "key": "A",
            "text": "閰嶅鍙屽紩鍙峰唴 锛屼笉鍙互鏈夋眽瀛?,
            "textPlain": "閰嶅鍙屽紩鍙峰唴 锛屼笉鍙互鏈夋眽瀛?,
            "images": []
          },
          {
            "key": "B",
            "text": "閰嶅鍙屽紩鍙峰彲浠ョ浉搴旀敼鍙樹负鑻扁絺鍗曞紩鍙封浇杈撳嚭鏁堟灉涓嶅彉",
            "textPlain": "閰嶅鍙屽紩鍙峰彲浠ョ浉搴旀敼鍙樹负鑻扁絺鍗曞紩鍙封浇杈撳嚭鏁堟灉涓嶅彉",
            "images": []
          },
          {
            "key": "C",
            "text": "閰嶅鍙屽紩鍙峰彲浠ョ浉搴旀敼鍙樹负涓変釜杩炵画鑻扁絺鍗曞紩鍙封浇杈撳嚭鏁堟灉涓嶅彉",
            "textPlain": "閰嶅鍙屽紩鍙峰彲浠ョ浉搴旀敼鍙樹负涓変釜杩炵画鑻扁絺鍗曞紩鍙封浇杈撳嚭鏁堟灉涓嶅彉",
            "images": []
          },
          {
            "key": "D",
            "text": "閰嶅鍙屽紩鍙峰彲浠ョ浉搴旀敼鍙樹负涓変釜杩炵画鑻扁絺鍙屽紩鍙封浇杈撳嚭鏁堟灉涓嶅彉",
            "textPlain": "閰嶅鍙屽紩鍙峰彲浠ョ浉搴旀敼鍙樹负涓変釜杩炵画鑻扁絺鍙屽紩鍙封浇杈撳嚭鏁堟灉涓嶅彉",
            "images": []
          }
        ],
        "reviewStatus": "pending",
        "stem": "鏈夊叧涓嬪垪C++浠ｇ爜鐨勮娉?锛屾纭殑鏄? )銆俓n```cpp\nprintf(\"Hello,GESP!\");\n```",
        "stemText": "鏈夊叧涓嬪垪C++浠ｇ爜鐨勮娉?锛屾纭殑鏄? )銆?cpp printf(\"Hello,GESP!\");",
        "tags": [
          "GESP"
        ],
        "type": "single",
        "updatedAt": "2026-03-26T13:12:56.583Z"
      }
    },
    {
      "_id": "69c3b7c7d215db96b02d5127",
      "questionUid": "downloads-1103-q4",
      "adminNote": "",
      "detail": "",
      "issueType": "ambiguous",
      "levelTag": "gesp3",
      "paperQuestionNo": 4,
      "reportedAt": "2026-03-25T10:24:07.752Z",
      "reporterName": "榛勫湥娑?,
      "source": "downloads",
      "sourceDocId": 1103,
      "sourceTitle": "1103 - GESP 涓夌骇鏍烽锛圕++ 缁勶級",
      "status": "pending",
      "tags": [
        "downloads-import",
        "objective",
        "gesp",
        "sample",
        "涓€缁存暟缁?
      ],
      "type": "single",
      "question": {
        "_id": "69c0b260d215db96b0110aa2",
        "questionUid": "downloads-1103-q4",
        "answer": "C",
        "enabled": true,
        "explanation": "鍦?C++ 缂栫▼涓紝鏁扮粍鐨勯暱搴︼紙鍗冲畠鑳藉瓨鍌ㄧ殑鍏冪礌涓暟锛夐€氬父鐢卞叾瀹氫箟鏃剁殑鏂规嫭鍙?`[]` 涓殑鏁板€煎喅瀹氥€俓n\n1. **鑷姩鎺ㄥ闀垮害**锛氬鏋滃畾涔夋暟缁勬椂娌℃湁鍦ㄦ柟鎷彿鍐呮寚瀹氬叿浣撶殑鏁板€硷紝鑰屾槸鐩存帴閫氳繃澶ф嫭鍙?`{}` 杩涜鍒濆鍖栵紙渚嬪 `int arr[] = {1, 2, 3, 4, 5};`锛夛紝缂栬瘧鍣ㄤ細鏍规嵁鍒濆鍖栧垪琛ㄤ腑鐨勫厓绱犱釜鏁拌嚜鍔ㄧ‘瀹氭暟缁勭殑闀垮害銆俓n2. **璁℃暟**锛氬湪甯歌鐨?GESP 鑰冮涓紝璇ヤ唬鐮侀€氬父涓?`int arr[] = {1, 2, 3, 4, 5};`銆傚彲浠ョ湅鍒板ぇ鎷彿鍐呭叡鏈?5 涓厓绱狅紙1, 2, 3, 4, 5锛夈€俓n3. **缁撹**锛氬洜姝わ紝缂栬瘧鍣ㄤ細涓烘暟缁?`arr` 鍒嗛厤 5 涓暣鏁扮殑绌洪棿锛屾暟缁勭殑闀垮害灏辨槸 5銆俓n\n娉ㄦ剰锛氬鏋滀唬鐮佹槸 `int arr[10] = {1, 2, 3, 4, 5};`锛岃櫧鐒跺彧鍒濆鍖栦簡 5 涓€硷紝浣嗘暟缁勭殑闀垮害渚濈劧鏄畾涔夌殑 10銆備絾鍦ㄦ湰棰樼粰鍑虹殑閫夐」鍜屽父瑙佺殑鑰冮鑳屾櫙涓嬶紝鏈€绗﹀悎閫昏緫鐨勫垵濮嬪寲褰㈠紡鏄?`arr[] = {1, 2, 3, 4, 5}`锛屾晠閫?C銆?,
        "explanationText": "鍦?C++ 缂栫▼涓紝鏁扮粍鐨勯暱搴︼紙鍗冲畠鑳藉瓨鍌ㄧ殑鍏冪礌涓暟锛夐€氬父鐢卞叾瀹氫箟鏃剁殑鏂规嫭鍙?[] 涓殑鏁板€煎喅瀹氥€?1. 鑷姩鎺ㄥ闀垮害锛氬鏋滃畾涔夋暟缁勬椂娌℃湁鍦ㄦ柟鎷彿鍐呮寚瀹氬叿浣撶殑鏁板€硷紝鑰屾槸鐩存帴閫氳繃澶ф嫭鍙?{} 杩涜鍒濆鍖栵紙渚嬪 int arr[] = {1, 2, 3, 4, 5};锛夛紝缂栬瘧鍣ㄤ細鏍规嵁鍒濆鍖栧垪琛ㄤ腑鐨勫厓绱犱釜鏁拌嚜鍔ㄧ‘瀹氭暟缁勭殑闀垮害銆?2. 璁℃暟锛氬湪甯歌鐨?GESP 鑰冮涓紝璇ヤ唬鐮侀€氬父涓?int arr[] = {1, 2, 3, 4, 5};銆傚彲浠ョ湅鍒板ぇ鎷彿鍐呭叡鏈?5 涓厓绱狅紙1, 2, 3, 4, 5锛夈€?3. 缁撹锛氬洜姝わ紝缂栬瘧鍣ㄤ細涓烘暟缁?arr 鍒嗛厤 5 涓暣鏁扮殑绌洪棿锛屾暟缁勭殑闀垮害灏辨槸 5銆?娉ㄦ剰锛氬鏋滀唬鐮佹槸 int arr[10] = {1, 2, 3, 4, 5};锛岃櫧鐒跺彧鍒濆鍖栦簡 5 涓€硷紝浣嗘暟缁勭殑闀垮害渚濈劧鏄畾涔夌殑 10銆備絾鍦ㄦ湰棰樼粰鍑虹殑閫夐」鍜屽父瑙佺殑鑰冮鑳屾櫙涓嬶紝鏈€绗﹀悎閫昏緫鐨勫垵濮嬪寲褰㈠紡鏄?arr[] = {1, 2, 3, 4, 5}锛屾晠閫?C銆?,
        "levelTag": "gesp3",
        "options": [
          {
            "key": "A",
            "text": "3",
            "textPlain": "3",
            "images": []
          },
          {
            "key": "B",
            "text": "4",
            "textPlain": "4",
            "images": []
          },
          {
            "key": "C",
            "text": "5",
            "textPlain": "5",
            "images": []
          },
          {
            "key": "D",
            "text": "6",
            "textPlain": "6",
            "images": []
          }
        ],
        "reviewStatus": "pending",
        "stem": "鑻ユ湁浠ヤ笅浠ｇ爜锛屽垯鏁扮粍 arr 鐨勯暱搴︽槸锛?锛夛紵",
        "stemText": "鑻ユ湁浠ヤ笅浠ｇ爜锛屽垯鏁扮粍 arr 鐨勯暱搴︽槸锛?锛夛紵",
        "tags": [
          "downloads-import",
          "objective",
          "gesp",
          "sample",
          "涓€缁存暟缁?
        ],
        "type": "single",
        "updatedAt": "2026-03-23T04:02:47.056Z"
      }
    },
    {
      "_id": "69c38bb6d215db96b02abf01",
      "questionUid": "gesp-2024-09-cpp-1-q4",
      "adminNote": "",
      "detail": "鏃犺鍝釜閫夐」閮戒笉瀵癸紝鎸ㄤ釜璇曚篃鍏ㄩ敊",
      "issueType": "other",
      "levelTag": "gesp1",
      "paperQuestionNo": 4,
      "reportedAt": "2026-03-25T07:16:06.767Z",
      "reporterName": "鏈辨尟鍥?,
      "source": "gesp",
      "sourceDocId": 271,
      "sourceTitle": "GESP-C++-2024骞?鏈堜竴绾х湡棰樺嵎GESP-C++-2024骞?鏈堜竴绾х湡棰樺嵎",
      "status": "pending",
      "tags": [
        "鏁板鍩虹"
      ],
      "type": "single",
      "question": {
        "_id": "69beb5e2d215db96b0fd0329",
        "questionUid": "gesp-2024-09-cpp-1-q4",
        "answer": "",
        "enabled": true,
        "explanation": "",
        "explanationText": "",
        "levelTag": "gesp1",
        "options": [
          {
            "key": "A",
            "text": "14",
            "textPlain": "14",
            "images": []
          },
          {
            "key": "B",
            "text": "4",
            "textPlain": "4",
            "images": []
          },
          {
            "key": "C",
            "text": "1",
            "textPlain": "1",
            "images": []
          },
          {
            "key": "D",
            "text": "0",
            "textPlain": "0",
            "images": []
          }
        ],
        "reviewStatus": "pending",
        "stem": "C++琛ㄨ揪寮?`10 - 3 * 2` 鐨勫€兼槸( )銆?,
        "stemText": "C++琛ㄨ揪寮?10 - 3 * 2 鐨勫€兼槸( )銆?,
        "tags": [
          "鏁板鍩虹"
        ],
        "type": "single",
        "updatedAt": "2026-03-26T13:58:28.993Z"
      }
    },
    {
      "_id": "69c29aeed215db96b0224794",
      "questionUid": "gesp-2024-06-cpp-1-q2",
      "adminNote": "",
      "detail": "",
      "issueType": "wrong_answer",
      "levelTag": "gesp1",
      "paperQuestionNo": 2,
      "reportedAt": "2026-03-24T14:08:46.232Z",
      "reporterName": "鍚村郴涓?,
      "source": "gesp",
      "sourceDocId": 263,
      "sourceTitle": "GESP-C++-2024骞?鏈堜竴绾х湡棰樺嵎GESP-C++-2024骞?鏈堜竴绾х湡棰樺嵎",
      "status": "pending",
      "tags": [
        "GESP"
      ],
      "type": "single",
      "question": {
        "_id": "69beb5e2d215db96b0fd0261",
        "questionUid": "gesp-2024-06-cpp-1-q2",
        "answer": "D",
        "enabled": true,
        "explanation": "鏈鑰冨療C++涓繍绠楃鐨勪紭鍏堢骇鍜屾暣鏁伴櫎娉曠殑鐗规€с€俓n\nC++琛ㄨ揪寮?`3 - 3 * 3 / 5` 鐨勮绠楁楠ゅ涓嬶細\n\n1.  **杩愮畻绗︿紭鍏堢骇**锛歕n    *   涔樻硶 `*` 鍜?闄ゆ硶 `/` 鐨勪紭鍏堢骇楂樹簬鍑忔硶 `-`銆俓n    *   涔樻硶 `*` 鍜?闄ゆ硶 `/` 鐨勪紭鍏堢骇鐩稿悓锛屽畠浠粠宸﹀埌鍙崇粨鍚堛€俓n\n2.  **璁＄畻杩囩▼**锛歕n    *   棣栧厛璁＄畻鏈€宸﹁竟鐨勪箻娉?`3 * 3`锛歕n        `3 * 3 = 9`\n        琛ㄨ揪寮忓彉涓?`3 - 9 / 5`\n\n    *   鎺ョ潃璁＄畻闄ゆ硶 `9 / 5`锛歕n        鍦–++涓紝濡傛灉闄ゆ硶鐨勪袱涓搷浣滄暟閮芥槸鏁存暟锛岄偅涔堟墽琛岀殑鏄暣鏁伴櫎娉曘€傛暣鏁伴櫎娉曠殑缁撴灉浼氭埅鏂皬鏁伴儴鍒嗭紙鍚戦浂鍙栨暣锛夈€俓n        `9 / 5 = 1` (鍥犱负 9 闄や互 5 绛変簬 1 浣?4锛屾暣鏁伴櫎娉曠粨鏋滄槸 1)\n        琛ㄨ揪寮忓彉涓?`3 - 1`\n\n    *   鏈€鍚庤绠楀噺娉?`3 - 1`锛歕n        `3 - 1 = 2`\n\n鍥犳锛岃〃杈惧紡 `3 - 3 * 3 / 5` 鐨勫€兼槸 `2`銆俓n\n瀵瑰簲閫夐」锛屾纭瓟妗堟槸 D銆?,
        "explanationText": "鏈鑰冨療C++涓繍绠楃鐨勪紭鍏堢骇鍜屾暣鏁伴櫎娉曠殑鐗规€с€?C++琛ㄨ揪寮?3 - 3 * 3 / 5 鐨勮绠楁楠ゅ涓嬶細 1. 杩愮畻绗︿紭鍏堢骇锛?* 涔樻硶 鍜?闄ゆ硶 / 鐨勪紭鍏堢骇楂樹簬鍑忔硶 -銆?* 涔樻硶 鍜?闄ゆ硶 / 鐨勪紭鍏堢骇鐩稿悓锛屽畠浠粠宸﹀埌鍙崇粨鍚堛€?2. 璁＄畻杩囩▼锛?* 棣栧厛璁＄畻鏈€宸﹁竟鐨勪箻娉?3 * 3锛?3 * 3 = 9 琛ㄨ揪寮忓彉涓?3 - 9 / 5 * 鎺ョ潃璁＄畻闄ゆ硶 9 / 5锛?鍦–++涓紝濡傛灉闄ゆ硶鐨勪袱涓搷浣滄暟閮芥槸鏁存暟锛岄偅涔堟墽琛岀殑鏄暣鏁伴櫎娉曘€傛暣鏁伴櫎娉曠殑缁撴灉浼氭埅鏂皬鏁伴儴鍒嗭紙鍚戦浂鍙栨暣锛夈€?9 / 5 = 1 (鍥犱负 9 闄や互 5 绛変簬 1 浣?4锛屾暣鏁伴櫎娉曠粨鏋滄槸 1) 琛ㄨ揪寮忓彉涓?3 - 1 * 鏈€鍚庤绠楀噺娉?3 - 1锛?3 - 1 = 2 鍥犳锛岃〃杈惧紡 3 - 3 * 3 / 5 鐨勫€兼槸 2銆?瀵瑰簲閫夐」锛屾纭瓟妗堟槸 D銆?,
        "levelTag": "gesp1",
        "options": [
          {
            "key": "A",
            "text": "1.2",
            "textPlain": "1.2",
            "images": []
          },
          {
            "key": "B",
            "text": "1",
            "textPlain": "1",
            "images": []
          },
          {
            "key": "C",
            "text": "0",
            "textPlain": "0",
            "images": []
          },
          {
            "key": "D",
            "text": "2",
            "textPlain": "2",
            "images": []
          }
        ],
        "reviewStatus": "pending",
        "stem": "C++琛ㄨ揪寮?`3 - 3 * 3 / 5` 鐨勫€兼槸( )",
        "stemText": "C++琛ㄨ揪寮?3 - 3 * 3 / 5 鐨勫€兼槸( )",
        "tags": [
          "GESP"
        ],
        "type": "single",
        "updatedAt": "2026-03-26T07:51:53.448Z"
      }
    },
    {
      "_id": "69c29570d215db96b02203cb",
      "questionUid": "gesp-2023-12-cpp-6-q21",
      "adminNote": "",
      "detail": "鍙湁鍥涜浠ｇ爜",
      "issueType": "other",
      "levelTag": "gesp6",
      "paperQuestionNo": 21,
      "reportedAt": "2026-03-24T13:45:20.699Z",
      "reporterName": "鏉庣汗钀?,
      "source": "gesp",
      "sourceDocId": 233,
      "sourceTitle": "GESP-C++-2023骞?2鏈堝叚绾х湡棰樺嵎GESP-C++-2023骞?2鏈堝叚绾х湡棰樺嵎",
      "status": "pending",
      "tags": [
        "GESP"
      ],
      "type": "judge",
      "question": {
        "_id": "69beb5e2d215db96b0fd0160",
        "questionUid": "gesp-2023-12-cpp-6-q21",
        "answer": "false",
        "enabled": true,
        "explanation": "棰樼洰涓殑闄堣堪鏄敊璇殑銆俓n\n璇︾粏瑙ｆ瀽濡備笅锛歕n\n1.  **`delete ptr` 鐨勪綔鐢?*锛歕n    *   `int * ptr = new int(10);` 杩欒浠ｇ爜鍦ㄥ爢涓婂垎閰嶄簡涓€鍧楀唴瀛樻潵瀛樺偍鏁存暟 `10`锛屽苟灏嗚繖鍧楀唴瀛樼殑鍦板潃璧嬬粰浜嗘寚閽堝彉閲?`ptr`銆俙ptr` 鏈韩鏄竴涓寚閽堝彉閲忥紝閫氬父瀛樺偍鍦ㄦ爤涓婏紙濡傛灉瀹冨湪鍑芥暟鍐呴儴澹版槑锛夈€俓n    *   `delete ptr;` 杩欒浠ｇ爜鐨勪綔鐢ㄦ槸**閲婃斁 `ptr` 鎵€鎸囧悜鐨勫爢鍐呭瓨**銆備篃灏辨槸璇达紝涔嬪墠瀛樺偍 `10` 鐨勯偅鍧楀唴瀛樿褰掕繕缁欎簡绯荤粺锛屼笉鍐嶅睘浜庣▼搴忔墍鏈夈€俓n    *   **鍏抽敭鐐癸細`delete ptr;` 骞舵病鏈夊垹闄ゆ寚閽堝彉閲?`ptr` 鏈韩銆?* 鎸囬拡鍙橀噺 `ptr` 浠嶇劧瀛樺湪锛屽苟涓斿畠浠嶇劧瀛樺偍鐫€閭ｅ潡宸茬粡琚噴鏀剧殑鍐呭瓨鍦板潃銆傛鏃讹紝`ptr` 鎴愪负浜嗕竴涓€滄偓绌烘寚閽堚€濓紙dangling pointer锛夈€俓n\n2.  **棰樼洰闄堣堪鐨勯敊璇箣澶?*锛歕n    *   棰樼洰涓锛氣€滅敱浜庡垹闄や簡鍙橀噺 `ptr`鈥濄€傝繖閮ㄥ垎鏄敊璇殑銆俙delete ptr` 骞舵病鏈夊垹闄ゅ彉閲?`ptr`銆傚彉閲?`ptr` 浠嶇劧瀛樺湪浜庡叾浣滅敤鍩熷唴銆俓n    *   铏界劧鈥渀ptr` 鎵€瀵瑰簲鐨勬暟鎹篃闅忎箣鍒犻櫎鈥濊繖閮ㄥ垎锛堟寚鍫嗕笂鐨勬暟鎹?`10`锛夋槸姝ｇ‘鐨勶紝浣嗗叾鍓嶆彁鈥滃垹闄や簡鍙橀噺 `ptr`鈥濇槸閿欒鐨勩€俓n\n3.  **绗?8 琛屼唬鐮侊紙鍗?`cout<<*ptr<<endl;`锛夌殑鎵ц缁撴灉**锛歕n    *   鍦?`delete ptr;` 涔嬪悗锛宍ptr` 鎴愪负浜嗕竴涓偓绌烘寚閽堛€俓n    *   `cout<<*ptr<<endl;` 灏濊瘯瑙ｅ紩鐢ㄤ竴涓偓绌烘寚閽堬紝鍗宠闂竴鍧楀凡缁忚閲婃斁鐨勫唴瀛樸€傝繖绉嶈涓哄湪 C++ 涓绉颁负**鏈畾涔夎涓猴紙Undefined Behavior锛?*銆俓n    *   鏈畾涔夎涓烘剰鍛崇潃绋嬪簭鍙兘鍙戠敓浠讳綍浜嬫儏锛氬畠鍙兘宕╂簝锛堟姤鍛婇敊璇紝渚嬪娈甸敊璇?璁块棶鍐茬獊锛夈€佸彲鑳芥墦鍗板嚭鏃х殑鍊硷紙濡傛灉鍐呭瓨灏氭湭琚搷浣滅郴缁熷洖鏀舵垨瑕嗙洊锛夈€佸彲鑳芥墦鍗板嚭鍨冨溇鍊硷紝涔熷彲鑳界湅浼兼甯歌繍琛屼絾瀵艰嚧鍚庣画鐨勫唴瀛橀敊璇€傚畠**涓嶄繚璇?*涓€瀹氫細鈥滄姤閿欌€濇垨宕╂簝銆俓n\n**鎬荤粨**锛歕n棰樼洰涓殑鏍稿績閿欒鍦ㄤ簬鍏跺墠鎻愶細鈥滃垹闄や簡鍙橀噺 `ptr`鈥濄€俙delete` 鎿嶄綔绗︽槸鐢ㄦ潵閲婃斁鎸囬拡鎵€鎸囧悜鐨勫爢鍐呭瓨锛岃€屼笉鏄垹闄ゆ寚閽堝彉閲忔湰韬€傜敱浜庤繖涓墠鎻愭槸閿欒鐨勶紝鍥犳鏁翠釜闄堣堪鐨勬帹鐞嗛摼鏄敊璇殑锛屽嵆浣垮悗缁殑缁撴灉锛堣闂凡閲婃斁鍐呭瓨鍙兘瀵艰嚧閿欒锛夊湪鏌愪簺鎯呭喌涓嬫槸姝ｇ‘鐨勶紝浣嗗叾鎺ㄥ杩囩▼鏄熀浜庨敊璇殑鍓嶆彁銆俓n\n鍥犳锛岃闄堣堪鏄敊璇殑銆俓n\nThe final answer is $\\boxed{B}$",
        "explanationText": "棰樼洰涓殑闄堣堪鏄敊璇殑銆?璇︾粏瑙ｆ瀽濡備笅锛?1. delete ptr 鐨勪綔鐢細 * int * ptr = new int(10); 杩欒浠ｇ爜鍦ㄥ爢涓婂垎閰嶄簡涓€鍧楀唴瀛樻潵瀛樺偍鏁存暟 10锛屽苟灏嗚繖鍧楀唴瀛樼殑鍦板潃璧嬬粰浜嗘寚閽堝彉閲?ptr銆俻tr 鏈韩鏄竴涓寚閽堝彉閲忥紝閫氬父瀛樺偍鍦ㄦ爤涓婏紙濡傛灉瀹冨湪鍑芥暟鍐呴儴澹版槑锛夈€?* delete ptr; 杩欒浠ｇ爜鐨勪綔鐢ㄦ槸閲婃斁 ptr 鎵€鎸囧悜鐨勫爢鍐呭瓨銆備篃灏辨槸璇达紝涔嬪墠瀛樺偍 10 鐨勯偅鍧楀唴瀛樿褰掕繕缁欎簡绯荤粺锛屼笉鍐嶅睘浜庣▼搴忔墍鏈夈€?* 鍏抽敭鐐癸細delete ptr; 骞舵病鏈夊垹闄ゆ寚閽堝彉閲?ptr 鏈韩銆?鎸囬拡鍙橀噺 ptr 浠嶇劧瀛樺湪锛屽苟涓斿畠浠嶇劧瀛樺偍鐫€閭ｅ潡宸茬粡琚噴鏀剧殑鍐呭瓨鍦板潃銆傛鏃讹紝ptr 鎴愪负浜嗕竴涓€滄偓绌烘寚閽堚€濓紙dangling pointer锛夈€?2. 棰樼洰闄堣堪鐨勯敊璇箣澶勶細 * 棰樼洰涓锛氣€滅敱浜庡垹闄や簡鍙橀噺 ptr鈥濄€傝繖閮ㄥ垎鏄敊璇殑銆俤elete ptr 骞舵病鏈夊垹闄ゅ彉閲?ptr銆傚彉閲?ptr 浠嶇劧瀛樺湪浜庡叾浣滅敤鍩熷唴銆?* 铏界劧鈥減tr 鎵€瀵瑰簲鐨勬暟鎹篃闅忎箣鍒犻櫎鈥濊繖閮ㄥ垎锛堟寚鍫嗕笂鐨勬暟鎹?10锛夋槸姝ｇ‘鐨勶紝浣嗗叾鍓嶆彁鈥滃垹闄や簡鍙橀噺 ptr鈥濇槸閿欒鐨勩€?3. 绗?8 琛屼唬鐮侊紙鍗?cout<<ptr<<endl;锛夌殑鎵ц缁撴灉锛?* 鍦?delete ptr; 涔嬪悗锛宲tr 鎴愪负浜嗕竴涓偓绌烘寚閽堛€?* cout<<ptr<<endl; 灏濊瘯瑙ｅ紩鐢ㄤ竴涓偓绌烘寚閽堬紝鍗宠闂竴鍧楀凡缁忚閲婃斁鐨勫唴瀛樸€傝繖绉嶈涓哄湪 C++ 涓绉颁负鏈畾涔夎涓猴紙Undefined Behavior锛夈€?* 鏈畾涔夎涓烘剰鍛崇潃绋嬪簭鍙兘鍙戠敓浠讳綍浜嬫儏锛氬畠鍙兘宕╂簝锛堟姤鍛婇敊璇紝渚嬪娈甸敊璇?璁块棶鍐茬獊锛夈€佸彲鑳芥墦鍗板嚭鏃х殑鍊硷紙濡傛灉鍐呭瓨灏氭湭琚搷浣滅郴缁熷洖鏀舵垨瑕嗙洊锛夈€佸彲鑳芥墦鍗板嚭鍨冨溇鍊硷紝涔熷彲鑳界湅浼兼甯歌繍琛屼絾瀵艰嚧鍚庣画鐨勫唴瀛橀敊璇€傚畠涓嶄繚璇佷竴瀹氫細鈥滄姤閿欌€濇垨宕╂簝銆?鎬荤粨锛?棰樼洰涓殑鏍稿績閿欒鍦ㄤ簬鍏跺墠鎻愶細鈥滃垹闄や簡鍙橀噺 ptr鈥濄€俤elete 鎿嶄綔绗︽槸鐢ㄦ潵閲婃斁鎸囬拡鎵€鎸囧悜鐨勫爢鍐呭瓨锛岃€屼笉鏄垹闄ゆ寚閽堝彉閲忔湰韬€傜敱浜庤繖涓墠鎻愭槸閿欒鐨勶紝鍥犳鏁翠釜闄堣堪鐨勬帹鐞嗛摼鏄敊璇殑锛屽嵆浣垮悗缁殑缁撴灉锛堣闂凡閲婃斁鍐呭瓨鍙兘瀵艰嚧閿欒锛夊湪鏌愪簺鎯呭喌涓嬫槸姝ｇ‘鐨勶紝浣嗗叾鎺ㄥ杩囩▼鏄熀浜庨敊璇殑鍓嶆彁銆?鍥犳锛岃闄堣堪鏄敊璇殑銆?The final answer is $\\boxed{B}$",
        "levelTag": "gesp6",
        "options": [
          {
            "key": "true",
            "text": "",
            "textPlain": "",
            "images": []
          },
          {
            "key": "false",
            "text": "",
            "textPlain": "",
            "images": []
          }
        ],
        "reviewStatus": "pending",
        "stem": "鍦ㄤ笅闈?$C++$ 浠ｇ爜涓紝鐢变簬鍒犻櫎浜嗗彉閲?`ptr` 锛屽洜姝?`ptr` 鎵€瀵瑰簲鐨勬暟鎹篃闅忎箣鍒犻櫎锛屾晠绗?$8$ 琛屼唬鐮佽鎵ц鏃讹紝灏嗘姤閿欍€傦紙 锛塡n```cpp\nint * ptr=new int(10);\ncout<<*ptr<<endl;\ndelete ptr;\ncout<<*ptr<<endl;\n```",
        "stemText": "鍦ㄤ笅闈?$C++$ 浠ｇ爜涓紝鐢变簬鍒犻櫎浜嗗彉閲?ptr 锛屽洜姝?ptr 鎵€瀵瑰簲鐨勬暟鎹篃闅忎箣鍒犻櫎锛屾晠绗?$8$ 琛屼唬鐮佽鎵ц鏃讹紝灏嗘姤閿欍€傦紙 锛?cpp int * ptr=new int(10); cout<<ptr<<endl; delete ptr; cout<<ptr<<endl;",
        "tags": [
          "GESP",
          "鏍?
        ],
        "type": "judge",
        "updatedAt": "2026-03-25T09:11:35.882Z"
      }
    },
    {
      "_id": "69c28d1bd215db96b0218eed",
      "questionUid": "gesp-2024-03-cpp-3-q15",
      "adminNote": "",
      "detail": "",
      "issueType": "wrong_answer",
      "levelTag": "gesp3",
      "paperQuestionNo": 15,
      "reportedAt": "2026-03-24T13:09:47.441Z",
      "reporterName": "鏉庝紵姣?,
      "source": "gesp",
      "sourceDocId": 257,
      "sourceTitle": "GESP-C++-2024骞?鏈堜笁绾х湡棰樺嵎GESP-C++-2024骞?鏈堜笁绾х湡棰樺嵎",
      "status": "pending",
      "tags": [
        "GESP"
      ],
      "type": "single",
      "question": {
        "_id": "69beb5e2d215db96b0fd01d8",
        "questionUid": "gesp-2024-03-cpp-3-q15",
        "answer": "C",
        "enabled": true,
        "explanation": "鐜嬮€夊厛鐢熸槸涓浗璁＄畻鏈虹瀛︽妧鏈鍩熺殑鏉板嚭浠ｈ〃锛岃瑾変负鈥滄眽瀛楁縺鍏夌収鎺掓妧鏈箣鐖垛€濄€備粬鐨勬渶閲嶅ぇ璐＄尞鏄彂鏄庝簡姹夊瓧婵€鍏夌収鎺掔郴缁熴€傝繖椤规妧鏈交搴曟敼鍙樹簡涓浗娌跨敤浜嗕笂鍗冨勾鐨勯搮瀛楀嵃鍒锋柟寮忥紝瀹炵幇浜嗘眽瀛楀嵃鍒风殑鈥滃憡鍒搮涓庣伀锛岃繋鏉ュ厜涓庣數鈥濈殑闈╁懡锛屼负涓枃淇℃伅澶勭悊鍜屽嵃鍒峰嚭鐗堜笟鐨勭幇浠ｅ寲鍋氬嚭浜嗛噷绋嬬寮忕殑璐＄尞銆俓n\n閫夐」鍒嗘瀽锛歕nA. 鍒堕€犺嚜鍔ㄩ┚椹舵苯杞︼細杩欎笌鐜嬮€夊厛鐢熺殑鐮旂┒棰嗗煙鍜岃础鐚棤鍏炽€傝嚜鍔ㄩ┚椹舵苯杞︽槸杩戝勾鏉ュ叴璧风殑浜哄伐鏅鸿兘鍜屾苯杞﹀伐绋嬩氦鍙夐鍩熴€俓nB. 鍒涚珛鍩硅瀛︽牎锛氳櫧鐒剁帇閫夊厛鐢熷湪鏁欒偛棰嗗煙鏈夎础鐚紝浣嗗垱绔嬪煿璁鏍″苟闈炲叾鏈€閲嶅ぇ鐨勬妧鏈础鐚€俓nC. 鍙戞槑姹夊瓧婵€鍏夌収鎺掔郴缁燂細杩欐槸鐜嬮€夊厛鐢熸渶鏍稿績銆佹渶骞夸负浜虹煡涓斿叿鏈夊垝鏃朵唬鎰忎箟鐨勯噸澶ц础鐚€備粬棰嗗鐮斿埗浜嗘眽瀛椾俊鎭鐞嗕笌婵€鍏夌収鎺掔郴缁燂紝浣夸腑鏂囧嚭鐗堝嵃鍒疯繘鍏ヤ簡鏁板瓧鍖栨椂浠ｃ€俓nD. 鎴愮珛鏂规鍏徃锛氭柟姝ｅ叕鍙告槸鍩轰簬鐜嬮€夊厛鐢熺殑姹夊瓧婵€鍏夌収鎺掓妧鏈€屾垚绔嬬殑锛屾棬鍦ㄥ皢杩欓」鎶€鏈骇涓氬寲銆傛垚绔嬪叕鍙告槸鎶€鏈垚鏋滆浆鍖栧拰浜т笟鍖栫殑浣撶幇锛屼絾鍏舵牴鏈拰鏈€閲嶅ぇ鐨勮础鐚槸鎶€鏈湰韬殑鈥滃彂鏄庘€濄€俓n\n鍥犳锛岀帇閫夊厛鐢熺殑閲嶅ぇ璐＄尞鏄彂鏄庢眽瀛楁縺鍏夌収鎺掔郴缁熴€?,
        "explanationText": "鐜嬮€夊厛鐢熸槸涓浗璁＄畻鏈虹瀛︽妧鏈鍩熺殑鏉板嚭浠ｈ〃锛岃瑾変负鈥滄眽瀛楁縺鍏夌収鎺掓妧鏈箣鐖垛€濄€備粬鐨勬渶閲嶅ぇ璐＄尞鏄彂鏄庝簡姹夊瓧婵€鍏夌収鎺掔郴缁熴€傝繖椤规妧鏈交搴曟敼鍙樹簡涓浗娌跨敤浜嗕笂鍗冨勾鐨勯搮瀛楀嵃鍒锋柟寮忥紝瀹炵幇浜嗘眽瀛楀嵃鍒风殑鈥滃憡鍒搮涓庣伀锛岃繋鏉ュ厜涓庣數鈥濈殑闈╁懡锛屼负涓枃淇℃伅澶勭悊鍜屽嵃鍒峰嚭鐗堜笟鐨勭幇浠ｅ寲鍋氬嚭浜嗛噷绋嬬寮忕殑璐＄尞銆?閫夐」鍒嗘瀽锛?A. 鍒堕€犺嚜鍔ㄩ┚椹舵苯杞︼細杩欎笌鐜嬮€夊厛鐢熺殑鐮旂┒棰嗗煙鍜岃础鐚棤鍏炽€傝嚜鍔ㄩ┚椹舵苯杞︽槸杩戝勾鏉ュ叴璧风殑浜哄伐鏅鸿兘鍜屾苯杞﹀伐绋嬩氦鍙夐鍩熴€?B. 鍒涚珛鍩硅瀛︽牎锛氳櫧鐒剁帇閫夊厛鐢熷湪鏁欒偛棰嗗煙鏈夎础鐚紝浣嗗垱绔嬪煿璁鏍″苟闈炲叾鏈€閲嶅ぇ鐨勬妧鏈础鐚€?C. 鍙戞槑姹夊瓧婵€鍏夌収鎺掔郴缁燂細杩欐槸鐜嬮€夊厛鐢熸渶鏍稿績銆佹渶骞夸负浜虹煡涓斿叿鏈夊垝鏃朵唬鎰忎箟鐨勯噸澶ц础鐚€備粬棰嗗鐮斿埗浜嗘眽瀛椾俊鎭鐞嗕笌婵€鍏夌収鎺掔郴缁燂紝浣夸腑鏂囧嚭鐗堝嵃鍒疯繘鍏ヤ簡鏁板瓧鍖栨椂浠ｃ€?D. 鎴愮珛鏂规鍏徃锛氭柟姝ｅ叕鍙告槸鍩轰簬鐜嬮€夊厛鐢熺殑姹夊瓧婵€鍏夌収鎺掓妧鏈€屾垚绔嬬殑锛屾棬鍦ㄥ皢杩欓」鎶€鏈骇涓氬寲銆傛垚绔嬪叕鍙告槸鎶€鏈垚鏋滆浆鍖栧拰浜т笟鍖栫殑浣撶幇锛屼絾鍏舵牴鏈拰鏈€閲嶅ぇ鐨勮础鐚槸鎶€鏈湰韬殑鈥滃彂鏄庘€濄€?鍥犳锛岀帇閫夊厛鐢熺殑閲嶅ぇ璐＄尞鏄彂鏄庢眽瀛楁縺鍏夌収鎺掔郴缁熴€?,
        "levelTag": "gesp3",
        "options": [
          {
            "key": "A",
            "text": "鍒堕€犫緝鍔ㄩ┚椹舵苯杞?,
            "textPlain": "鍒堕€犫緝鍔ㄩ┚椹舵苯杞?,
            "images": []
          },
          {
            "key": "B",
            "text": "鍒涒酱鍩硅瀛︽牎",
            "textPlain": "鍒涒酱鍩硅瀛︽牎",
            "images": []
          },
          {
            "key": "C",
            "text": "鍙戞槑姹夊瓧婵€鍏夌収鎺掔郴缁?,
            "textPlain": "鍙戞槑姹夊瓧婵€鍏夌収鎺掔郴缁?,
            "images": []
          },
          {
            "key": "D",
            "text": "鎴愨酱饨呮鍏徃",
            "textPlain": "鎴愨酱饨呮鍏徃",
            "images": []
          }
        ],
        "reviewStatus": "pending",
        "stem": "涓浗璁＄畻鏈哄浼氾紙CCF锛?鍦?024骞?饨?27饨?鐨勯濂栧吀绀间笂棰佸竷浜嗙帇閫夊锛?鐜嬮€夊厛饨ｇ殑閲嶁激璐＄尞鏄紙 锛?銆?,
        "stemText": "涓浗璁＄畻鏈哄浼氾紙CCF锛?鍦?024骞?饨?27饨?鐨勯濂栧吀绀间笂棰佸竷浜嗙帇閫夊锛?鐜嬮€夊厛饨ｇ殑閲嶁激璐＄尞鏄紙 锛?銆?,
        "tags": [
          "GESP"
        ],
        "type": "single",
        "updatedAt": "2026-03-25T14:35:05.086Z"
      }
    },
    {
      "_id": "69c28cf4d215db96b0218cac",
      "questionUid": "gesp-2023-09-cpp-3-q17",
      "adminNote": "",
      "detail": "",
      "issueType": "wrong_answer",
      "levelTag": "gesp3",
      "paperQuestionNo": 17,
      "reportedAt": "2026-03-24T13:09:08.733Z",
      "reporterName": "鏉庝紵姣?,
      "source": "gesp",
      "sourceDocId": 242,
      "sourceTitle": "GESP-C++-2023骞?鏈堜笁绾х湡棰樺嵎GESP-C++-2023骞?鏈堜笁绾х湡棰樺嵎",
      "status": "pending",
      "tags": [
        "GESP"
      ],
      "type": "judge",
      "question": {
        "_id": "69beb5e2d215db96b0fd007b",
        "questionUid": "gesp-2023-09-cpp-3-q17",
        "answer": "",
        "enabled": true,
        "explanation": "",
        "explanationText": "",
        "levelTag": "gesp3",
        "options": [
          {
            "key": "true",
            "text": "",
            "textPlain": "",
            "images": []
          },
          {
            "key": "false",
            "text": "",
            "textPlain": "",
            "images": []
          }
        ],
        "reviewStatus": "pending",
        "stem": "鍦–++璇█涓紝浣嶈繍绠楃涔熸湁绫讳技鈥滃厛涔橀櫎銆佸悗鍔犲噺鈥濈殑浼樺厛绾ц鍒欍€傚洜姝わ紝浣跨敤鏃跺簲娉ㄦ剰鍚堢悊浣跨敤鎷彿銆?,
        "stemText": "鍦–++璇█涓紝浣嶈繍绠楃涔熸湁绫讳技鈥滃厛涔橀櫎銆佸悗鍔犲噺鈥濈殑浼樺厛绾ц鍒欍€傚洜姝わ紝浣跨敤鏃跺簲娉ㄦ剰鍚堢悊浣跨敤鎷彿銆?,
        "tags": [
          "GESP",
          "浣嶈繍绠?
        ],
        "type": "judge",
        "updatedAt": "2026-03-26T07:54:28.535Z"
      }
    },
    {
      "_id": "69c14fcad215db96b016cfab",
      "questionUid": "downloads-1103-q13",
      "adminNote": "",
      "detail": "",
      "issueType": "wrong_answer",
      "levelTag": "gesp3",
      "paperQuestionNo": 13,
      "reportedAt": "2026-03-23T14:35:54.377Z",
      "reporterName": "鏉庢辰璧?,
      "source": "downloads",
      "sourceDocId": 1103,
      "sourceTitle": "1103 - GESP 涓夌骇鏍烽锛圕++ 缁勶級",
      "status": "pending",
      "tags": [
        "downloads-import",
        "objective",
        "gesp",
        "sample",
        "椤哄簭缁撴瀯",
        "鏉′欢缁撴瀯",
        "寰幆缁撴瀯"
      ],
      "type": "single",
      "question": {
        "_id": "69c0b260d215db96b0110aab",
        "questionUid": "downloads-1103-q13",
        "answer": "D",
        "enabled": true,
        "explanation": "鎴戜滑鍙互鎸夌収娴佺▼鍥剧殑閫昏緫姝ラ锛屽皢杈撳叆 a=1, b=2, c=3 浠ｅ叆杩涜妯℃嫙杩愯锛歕n\n1. 杈撳叆闃舵锛歛 = 1, b = 2, c = 3銆俓n2. 绗竴涓垽鏂锛氬垽鏂?a > b 鏄惁鎴愮珛銆傛鏃?1 > 2 涓嶆垚绔嬶紙缁撴灉涓衡€滃惁鈥?No锛夈€俓n3. 杩涘叆鈥滃惁鈥濆垎鏀細鎺ヤ笅鏉ュ垽鏂?b > c 鏄惁鎴愮珛銆傛鏃?2 > 3 涓嶆垚绔嬶紙缁撴灉涓衡€滃惁鈥?No锛夈€俓n4. 杩涘叆鈥滃惁鈥濆垎鏀細鎵ц鈥滆緭鍑?c鈥濈殑鎿嶄綔銆俓n5. 杈撳嚭缁撴灉锛氱敱浜?c 鐨勫€兼槸 3锛屾墍浠ョ▼搴忚緭鍑?3銆俓n\n鎬荤粨锛氳娴佺▼鍥剧殑閫昏緫鏄瘮杈冧笁涓暟鐨勫ぇ灏忓苟杈撳嚭鍏朵腑鐨勬渶澶у€笺€傚湪杈撳叆 1, 2, 3 鐨勬儏鍐典笅锛屾渶澶у€兼槸 3锛屽洜姝よ緭鍑?3銆傛纭€夐」涓?D銆?,
        "explanationText": "鎴戜滑鍙互鎸夌収娴佺▼鍥剧殑閫昏緫姝ラ锛屽皢杈撳叆 a=1, b=2, c=3 浠ｅ叆杩涜妯℃嫙杩愯锛?1. 杈撳叆闃舵锛歛 = 1, b = 2, c = 3銆?2. 绗竴涓垽鏂锛氬垽鏂?a > b 鏄惁鎴愮珛銆傛鏃?1 > 2 涓嶆垚绔嬶紙缁撴灉涓衡€滃惁鈥?No锛夈€?3. 杩涘叆鈥滃惁鈥濆垎鏀細鎺ヤ笅鏉ュ垽鏂?b > c 鏄惁鎴愮珛銆傛鏃?2 > 3 涓嶆垚绔嬶紙缁撴灉涓衡€滃惁鈥?No锛夈€?4. 杩涘叆鈥滃惁鈥濆垎鏀細鎵ц鈥滆緭鍑?c鈥濈殑鎿嶄綔銆?5. 杈撳嚭缁撴灉锛氱敱浜?c 鐨勫€兼槸 3锛屾墍浠ョ▼搴忚緭鍑?3銆?鎬荤粨锛氳娴佺▼鍥剧殑閫昏緫鏄瘮杈冧笁涓暟鐨勫ぇ灏忓苟杈撳嚭鍏朵腑鐨勬渶澶у€笺€傚湪杈撳叆 1, 2, 3 鐨勬儏鍐典笅锛屾渶澶у€兼槸 3锛屽洜姝よ緭鍑?3銆傛纭€夐」涓?D銆?,
        "levelTag": "gesp3",
        "options": [
          {
            "key": "A",
            "text": "鏃犺緭鍑?,
            "textPlain": "鏃犺緭鍑?,
            "images": []
          },
          {
            "key": "B",
            "text": "1",
            "textPlain": "1",
            "images": []
          },
          {
            "key": "C",
            "text": "2",
            "textPlain": "2",
            "images": []
          },
          {
            "key": "D",
            "text": "3",
            "textPlain": "3",
            "images": []
          }
        ],
        "reviewStatus": "pending",
        "stem": "涓嬮潰娴佺▼鍥撅紝杈撳叆 1 2 3锛屼細杈撳嚭锛?锛塡n\n![image](https://cdn.luogu.com.cn/upload/image_hosting/mal2jmju.png)",
        "stemText": "涓嬮潰娴佺▼鍥撅紝杈撳叆 1 2 3锛屼細杈撳嚭锛?锛?,
        "tags": [
          "downloads-import",
          "objective",
          "gesp",
          "sample",
          "椤哄簭缁撴瀯",
          "鏉′欢缁撴瀯",
          "寰幆缁撴瀯"
        ],
        "type": "single",
        "updatedAt": "2026-03-25T13:06:48.973Z"
      }
    }
  ]
}
