{
  "name": "Midway",
  "author": "Macrospace",
  "width": 17,
  "height": 12,
  "mapData": [
    [
      1,
      5,
      6,
      6,
      7,
      3,
      19,
      17,
      36,
      15,
      19,
      9,
      5,
      6,
      6,
      6,
      7
    ],
    [
      5,
      4,
      26,
      20,
      28,
      28,
      20,
      20,
      43,
      20,
      20,
      28,
      28,
      20,
      23,
      17,
      9
    ],
    [
      3,
      17,
      21,
      36,
      9,
      3,
      36,
      15,
      18,
      16,
      36,
      9,
      3,
      36,
      21,
      19,
      9
    ],
    [
      3,
      19,
      21,
      15,
      9,
      10,
      11,
      11,
      11,
      11,
      11,
      12,
      3,
      19,
      21,
      16,
      9
    ],
    [
      3,
      15,
      37,
      15,
      9,
      5,
      6,
      6,
      6,
      6,
      6,
      7,
      3,
      15,
      37,
      18,
      9
    ],
    [
      3,
      18,
      21,
      16,
      9,
      3,
      17,
      36,
      18,
      36,
      17,
      9,
      3,
      18,
      21,
      17,
      9
    ],
    [
      3,
      36,
      21,
      17,
      9,
      3,
      15,
      19,
      37,
      18,
      16,
      9,
      3,
      36,
      21,
      14,
      12
    ],
    [
      10,
      11,
      29,
      11,
      12,
      10,
      11,
      11,
      11,
      11,
      11,
      12,
      10,
      11,
      29,
      12,
      1
    ],
    [
      6,
      6,
      29,
      6,
      6,
      7,
      2,
      0,
      0,
      1,
      0,
      5,
      6,
      6,
      29,
      6,
      6
    ],
    [
      15,
      19,
      21,
      36,
      15,
      9,
      0,
      5,
      6,
      7,
      1,
      3,
      15,
      36,
      21,
      19,
      15
    ],
    [
      16,
      39,
      25,
      20,
      20,
      28,
      28,
      28,
      20,
      28,
      28,
      28,
      20,
      20,
      24,
      41,
      17
    ],
    [
      18,
      36,
      17,
      19,
      36,
      9,
      1,
      3,
      15,
      9,
      0,
      3,
      36,
      19,
      17,
      36,
      18
    ]
  ],
  "units": [
    {
      "type": "king",
      "team": "red",
      "x": 15,
      "y": 10
    },
    {
      "type": "king",
      "team": "blue",
      "x": 1,
      "y": 10
    },
    {
      "type": "king",
      "team": "green",
      "x": 8,
      "y": 1
    }
  ],
  "buildings": []
}